{
"meta":{"test_sets":[],"test_metrics":[],"learn_metrics":[{"best_value":"Min","name":"RMSE"}],"launch_mode":"Train","parameters":"","iteration_count":1000,"learn_sets":["learn"],"name":"experiment"},
"iterations":[
{"learn":[0.3878997293],"iteration":0,"passed_time":0.01243691829,"remaining_time":12.42448137},
{"learn":[0.3768732562],"iteration":1,"passed_time":0.01547089936,"remaining_time":7.719978781},
{"learn":[0.3665596149],"iteration":2,"passed_time":0.01812197142,"remaining_time":6.022535167},
{"learn":[0.3561411515],"iteration":3,"passed_time":0.02025392884,"remaining_time":5.04322828},
{"learn":[0.3461641572],"iteration":4,"passed_time":0.02183343896,"remaining_time":4.344854353},
{"learn":[0.3372349647],"iteration":5,"passed_time":0.02481592106,"remaining_time":4.111170923},
{"learn":[0.3287234539],"iteration":6,"passed_time":0.02808818904,"remaining_time":3.984510246},
{"learn":[0.3210521367],"iteration":7,"passed_time":0.03105408814,"remaining_time":3.85070693},
{"learn":[0.3132205107],"iteration":8,"passed_time":0.03264580636,"remaining_time":3.594666011},
{"learn":[0.3052952642],"iteration":9,"passed_time":0.03516513104,"remaining_time":3.481347973},
{"learn":[0.2975625681],"iteration":10,"passed_time":0.03851443915,"remaining_time":3.462798211},
{"learn":[0.2902139107],"iteration":11,"passed_time":0.040675396,"remaining_time":3.348940937},
{"learn":[0.2830498485],"iteration":12,"passed_time":0.04233452953,"remaining_time":3.214167742},
{"learn":[0.2765728281],"iteration":13,"passed_time":0.04402657907,"remaining_time":3.100729069},
{"learn":[0.2700213435],"iteration":14,"passed_time":0.0464515723,"remaining_time":3.050319915},
{"learn":[0.2637037432],"iteration":15,"passed_time":0.05029532887,"remaining_time":3.093162726},
{"learn":[0.2578218192],"iteration":16,"passed_time":0.05215958331,"remaining_time":3.0160512},
{"learn":[0.2519353805],"iteration":17,"passed_time":0.0554545175,"remaining_time":3.025352011},
{"learn":[0.2470552925],"iteration":18,"passed_time":0.05781792864,"remaining_time":2.985230947},
{"learn":[0.2418664328],"iteration":19,"passed_time":0.061171445,"remaining_time":2.997400805},
{"learn":[0.236745709],"iteration":20,"passed_time":0.06479958087,"remaining_time":3.020894746},
{"learn":[0.2318502974],"iteration":21,"passed_time":0.06861550466,"remaining_time":3.050271071},
{"learn":[0.2271213129],"iteration":22,"passed_time":0.07122320258,"remaining_time":3.025437779},
{"learn":[0.2229657599],"iteration":23,"passed_time":0.0746175098,"remaining_time":3.034445398},
{"learn":[0.2187846055],"iteration":24,"passed_time":0.07764161607,"remaining_time":3.028023027},
{"learn":[0.2147720597],"iteration":25,"passed_time":0.08084621873,"remaining_time":3.028623733},
{"learn":[0.2110425536],"iteration":26,"passed_time":0.08225056569,"remaining_time":2.964066682},
{"learn":[0.2070837452],"iteration":27,"passed_time":0.08374170257,"remaining_time":2.907033389},
{"learn":[0.2038580413],"iteration":28,"passed_time":0.08518188215,"remaining_time":2.852124399},
{"learn":[0.2005595623],"iteration":29,"passed_time":0.08676085061,"remaining_time":2.805267503},
{"learn":[0.1977368609],"iteration":30,"passed_time":0.08918405222,"remaining_time":2.787720858},
{"learn":[0.1946706448],"iteration":31,"passed_time":0.09074018781,"remaining_time":2.744890681},
{"learn":[0.1917397867],"iteration":32,"passed_time":0.0926947321,"remaining_time":2.716236544},
{"learn":[0.1887413898],"iteration":33,"passed_time":0.09417966078,"remaining_time":2.675810362},
{"learn":[0.1864629975],"iteration":34,"passed_time":0.09570854691,"remaining_time":2.638821365},
{"learn":[0.1837837141],"iteration":35,"passed_time":0.09769113232,"remaining_time":2.615951432},
{"learn":[0.1810537749],"iteration":36,"passed_time":0.09964038506,"remaining_time":2.593342995},
{"learn":[0.1787844052],"iteration":37,"passed_time":0.1041290454,"remaining_time":2.636108992},
{"learn":[0.1768316838],"iteration":38,"passed_time":0.1055102678,"remaining_time":2.599881215},
{"learn":[0.1745789793],"iteration":39,"passed_time":0.1069090732,"remaining_time":2.565817757},
{"learn":[0.1727017485],"iteration":40,"passed_time":0.1084169598,"remaining_time":2.535899132},
{"learn":[0.170590401],"iteration":41,"passed_time":0.1098205567,"remaining_time":2.504954604},
{"learn":[0.1686644491],"iteration":42,"passed_time":0.1118334332,"remaining_time":2.488944083},
{"learn":[0.1668104545],"iteration":43,"passed_time":0.1133908604,"remaining_time":2.46367415},
{"learn":[0.1648616698],"iteration":44,"passed_time":0.1151789081,"remaining_time":2.444352382},
{"learn":[0.1628300932],"iteration":45,"passed_time":0.116482257,"remaining_time":2.415740722},
{"learn":[0.1611638955],"iteration":46,"passed_time":0.1180821001,"remaining_time":2.394303008},
{"learn":[0.1595891618],"iteration":47,"passed_time":0.1198120655,"remaining_time":2.376272633},
{"learn":[0.157917306],"iteration":48,"passed_time":0.1212511618,"remaining_time":2.353262344},
{"learn":[0.156395296],"iteration":49,"passed_time":0.1236366558,"remaining_time":2.349096461},
{"learn":[0.1549295312],"iteration":50,"passed_time":0.1256074915,"remaining_time":2.337284498},
{"learn":[0.1535673541],"iteration":51,"passed_time":0.1271873349,"remaining_time":2.318722952},
{"learn":[0.1523742958],"iteration":52,"passed_time":0.1284822674,"remaining_time":2.295711457},
{"learn":[0.1511939236],"iteration":53,"passed_time":0.1298249072,"remaining_time":2.274340042},
{"learn":[0.1498528347],"iteration":54,"passed_time":0.1313637515,"remaining_time":2.257068094},
{"learn":[0.1488184501],"iteration":55,"passed_time":0.1328100143,"remaining_time":2.238797384},
{"learn":[0.1474799155],"iteration":56,"passed_time":0.1351659256,"remaining_time":2.236166102},
{"learn":[0.1464375889],"iteration":57,"passed_time":0.1377061248,"remaining_time":2.236537407},
{"learn":[0.1453642839],"iteration":58,"passed_time":0.1392387609,"remaining_time":2.220740237},
{"learn":[0.1441916927],"iteration":59,"passed_time":0.1407088149,"remaining_time":2.2044381},
{"learn":[0.1431935661],"iteration":60,"passed_time":0.14220416,"remaining_time":2.189011578},
{"learn":[0.1420473378],"iteration":61,"passed_time":0.1435960072,"remaining_time":2.172468625},
{"learn":[0.1412178405],"iteration":62,"passed_time":0.1449878961,"remaining_time":2.15640728},
{"learn":[0.1401695154],"iteration":63,"passed_time":0.1472103934,"remaining_time":2.152952003},
{"learn":[0.1393314935],"iteration":64,"passed_time":0.1487926951,"remaining_time":2.140325691},
{"learn":[0.1385296718],"iteration":65,"passed_time":0.1510244422,"remaining_time":2.137224682},
{"learn":[0.1375818167],"iteration":66,"passed_time":0.1527116168,"remaining_time":2.126566246},
{"learn":[0.136886565],"iteration":67,"passed_time":0.1540172574,"remaining_time":2.11094241},
{"learn":[0.1359958675],"iteration":68,"passed_time":0.1556893907,"remaining_time":2.10067859},
{"learn":[0.1349643392],"iteration":69,"passed_time":0.157244193,"remaining_time":2.089101421},
{"learn":[0.1341724124],"iteration":70,"passed_time":0.1591705712,"remaining_time":2.082668459},
{"learn":[0.1334733951],"iteration":71,"passed_time":0.160966827,"remaining_time":2.074683547},
{"learn":[0.1325860387],"iteration":72,"passed_time":0.162233135,"remaining_time":2.060138577},
{"learn":[0.1318240505],"iteration":73,"passed_time":0.1636694397,"remaining_time":2.048079745},
{"learn":[0.1309995602],"iteration":74,"passed_time":0.1660675168,"remaining_time":2.04816604},
{"learn":[0.1300604271],"iteration":75,"passed_time":0.1674987798,"remaining_time":2.036432534},
{"learn":[0.1294235948],"iteration":76,"passed_time":0.1690070831,"remaining_time":2.025890099},
{"learn":[0.1287422579],"iteration":77,"passed_time":0.1710591671,"remaining_time":2.022007077},
{"learn":[0.1279670243],"iteration":78,"passed_time":0.1729943784,"remaining_time":2.01680788},
{"learn":[0.1274549464],"iteration":79,"passed_time":0.1742533533,"remaining_time":2.003913563},
{"learn":[0.1268320094],"iteration":80,"passed_time":0.1756670334,"remaining_time":1.993061774},
{"learn":[0.1262063623],"iteration":81,"passed_time":0.1770820051,"remaining_time":1.982454643},
{"learn":[0.1256573506],"iteration":82,"passed_time":0.1784763939,"remaining_time":1.971841605},
{"learn":[0.1249891338],"iteration":83,"passed_time":0.1796480372,"remaining_time":1.959019072},
{"learn":[0.1243153184],"iteration":84,"passed_time":0.1831563005,"remaining_time":1.971623705},
{"learn":[0.12381037],"iteration":85,"passed_time":0.1846056049,"remaining_time":1.961971196},
{"learn":[0.1231513168],"iteration":86,"passed_time":0.1862771965,"remaining_time":1.954840004},
{"learn":[0.1227387798],"iteration":87,"passed_time":0.1874579646,"remaining_time":1.942746178},
{"learn":[0.1221324862],"iteration":88,"passed_time":0.1887655635,"remaining_time":1.932195824},
{"learn":[0.1215467107],"iteration":89,"passed_time":0.1922723267,"remaining_time":1.944086859},
{"learn":[0.1209329694],"iteration":90,"passed_time":0.1956075518,"remaining_time":1.953925985},
{"learn":[0.1205561962],"iteration":91,"passed_time":0.1981203766,"remaining_time":1.955361978},
{"learn":[0.1200490508],"iteration":92,"passed_time":0.1994905576,"remaining_time":1.945569201},
{"learn":[0.1196228037],"iteration":93,"passed_time":0.2011931069,"remaining_time":1.939159094},
{"learn":[0.1191951264],"iteration":94,"passed_time":0.2034333955,"remaining_time":1.937970768},
{"learn":[0.1187960981],"iteration":95,"passed_time":0.2073330676,"remaining_time":1.952386387},
{"learn":[0.1184570268],"iteration":96,"passed_time":0.2173414928,"remaining_time":2.023292453},
{"learn":[0.1179108129],"iteration":97,"passed_time":0.2203931401,"remaining_time":2.028516453},
{"learn":[0.117399744],"iteration":98,"passed_time":0.2222317284,"remaining_time":2.022533205},
{"learn":[0.1169314194],"iteration":99,"passed_time":0.2245501405,"remaining_time":2.020951264},
{"learn":[0.1165392527],"iteration":100,"passed_time":0.2261164425,"remaining_time":2.012660216},
{"learn":[0.1162093553],"iteration":101,"passed_time":0.2276869945,"remaining_time":2.004538442},
{"learn":[0.1155831815],"iteration":102,"passed_time":0.2297390368,"remaining_time":2.000737049},
{"learn":[0.1150959701],"iteration":103,"passed_time":0.2333822557,"remaining_time":2.010677896},
{"learn":[0.1146700087],"iteration":104,"passed_time":0.2368076873,"remaining_time":2.018503621},
{"learn":[0.1143313034],"iteration":105,"passed_time":0.2398715845,"remaining_time":2.023067892},
{"learn":[0.1139836891],"iteration":106,"passed_time":0.2430918535,"remaining_time":2.028794628},
{"learn":[0.113620964],"iteration":107,"passed_time":0.2464466198,"remaining_time":2.035466527},
{"learn":[0.1131972396],"iteration":108,"passed_time":0.2488883211,"remaining_time":2.034490771},
{"learn":[0.1127293836],"iteration":109,"passed_time":0.2503440003,"remaining_time":2.025510548},
{"learn":[0.1123862549],"iteration":110,"passed_time":0.2519039692,"remaining_time":2.017501158},
{"learn":[0.1120073675],"iteration":111,"passed_time":0.2645026759,"remaining_time":2.097128359},
{"learn":[0.1116502439],"iteration":112,"passed_time":0.2661746008,"remaining_time":2.08935284},
{"learn":[0.111287343],"iteration":113,"passed_time":0.267768319,"remaining_time":2.081076585},
{"learn":[0.1109580479],"iteration":114,"passed_time":0.2708293412,"remaining_time":2.084208408},
{"learn":[0.1105602336],"iteration":115,"passed_time":0.2726664295,"remaining_time":2.077906239},
{"learn":[0.1101687543],"iteration":116,"passed_time":0.2745753497,"remaining_time":2.072222511},
{"learn":[0.1098769534],"iteration":117,"passed_time":0.277351211,"remaining_time":2.07308278},
{"learn":[0.1095234347],"iteration":118,"passed_time":0.2800499487,"remaining_time":2.073310965},
{"learn":[0.1092428889],"iteration":119,"passed_time":0.2817121239,"remaining_time":2.065888908},
{"learn":[0.1089120687],"iteration":120,"passed_time":0.2830764299,"remaining_time":2.056398198},
{"learn":[0.10859531],"iteration":121,"passed_time":0.2845227761,"remaining_time":2.047631126},
{"learn":[0.1083973049],"iteration":122,"passed_time":0.2859833719,"remaining_time":2.039084692},
{"learn":[0.1082393569],"iteration":123,"passed_time":0.2874404261,"remaining_time":2.030627526},
{"learn":[0.1079423653],"iteration":124,"passed_time":0.2930451892,"remaining_time":2.051316324},
{"learn":[0.1076708731],"iteration":125,"passed_time":0.2950890234,"remaining_time":2.046887353},
{"learn":[0.1073838838],"iteration":126,"passed_time":0.2970402761,"remaining_time":2.041859536},
{"learn":[0.1071422177],"iteration":127,"passed_time":0.2988564065,"remaining_time":2.035959269},
{"learn":[0.1067730813],"iteration":128,"passed_time":0.3013732729,"remaining_time":2.034853649},
{"learn":[0.1064827142],"iteration":129,"passed_time":0.3035323131,"remaining_time":2.031331634},
{"learn":[0.1062002425],"iteration":130,"passed_time":0.3051195314,"remaining_time":2.024037197},
{"learn":[0.1059303275],"iteration":131,"passed_time":0.306439755,"remaining_time":2.015073541},
{"learn":[0.1056205118],"iteration":132,"passed_time":0.3081231381,"remaining_time":2.008592186},
{"learn":[0.105325962],"iteration":133,"passed_time":0.3097771467,"remaining_time":2.001992605},
{"learn":[0.1050012404],"iteration":134,"passed_time":0.3115186953,"remaining_time":1.996027196},
{"learn":[0.1046292863],"iteration":135,"passed_time":0.3130162487,"remaining_time":1.988573815},
{"learn":[0.1044343526],"iteration":136,"passed_time":0.3157016534,"remaining_time":1.988689977},
{"learn":[0.1042449404],"iteration":137,"passed_time":0.3178245693,"remaining_time":1.98525202},
{"learn":[0.1039601131],"iteration":138,"passed_time":0.3192365411,"remaining_time":1.977429222},
{"learn":[0.1037425509],"iteration":139,"passed_time":0.3207535108,"remaining_time":1.970342995},
{"learn":[0.1034639144],"iteration":140,"passed_time":0.3221642326,"remaining_time":1.962688481},
{"learn":[0.1032677725],"iteration":141,"passed_time":0.3239639884,"remaining_time":1.957472549},
{"learn":[0.1031731889],"iteration":142,"passed_time":0.3254628751,"remaining_time":1.950501286},
{"learn":[0.1029451619],"iteration":143,"passed_time":0.3278296195,"remaining_time":1.94876496},
{"learn":[0.102651816],"iteration":144,"passed_time":0.3292619242,"remaining_time":1.941509967},
{"learn":[0.1023269213],"iteration":145,"passed_time":0.3308878084,"remaining_time":1.935467044},
{"learn":[0.102217038],"iteration":146,"passed_time":0.3321340335,"remaining_time":1.927281161},
{"learn":[0.1020062461],"iteration":147,"passed_time":0.3335772964,"remaining_time":1.920323355},
{"learn":[0.1018546074],"iteration":148,"passed_time":0.3354063015,"remaining_time":1.915642702},
{"learn":[0.1016551806],"iteration":149,"passed_time":0.336766441,"remaining_time":1.908343166},
{"learn":[0.1014674918],"iteration":150,"passed_time":0.3382287452,"remaining_time":1.901696719},
{"learn":[0.1012624616],"iteration":151,"passed_time":0.3402665795,"remaining_time":1.898329338},
{"learn":[0.1010462833],"iteration":152,"passed_time":0.3417721744,"remaining_time":1.892032887},
{"learn":[0.1008410774],"iteration":153,"passed_time":0.3432367701,"remaining_time":1.885573426},
{"learn":[0.1006844167],"iteration":154,"passed_time":0.3444868702,"remaining_time":1.878009066},
{"learn":[0.100411308],"iteration":155,"passed_time":0.3460077981,"remaining_time":1.871990908},
{"learn":[0.1002398779],"iteration":156,"passed_time":0.3474231865,"remaining_time":1.865463352},
{"learn":[0.1000474778],"iteration":157,"passed_time":0.3497145574,"remaining_time":1.863668717},
{"learn":[0.09987534573],"iteration":158,"passed_time":0.3520200531,"remaining_time":1.861942545},
{"learn":[0.0996929213],"iteration":159,"passed_time":0.3534763156,"remaining_time":1.855750657},
{"learn":[0.09957352896],"iteration":160,"passed_time":0.354725749,"remaining_time":1.848539773},
{"learn":[0.09931993436],"iteration":161,"passed_time":0.3566262111,"remaining_time":1.844770154},
{"learn":[0.09903536602],"iteration":162,"passed_time":0.3581917215,"remaining_time":1.839303502},
{"learn":[0.09881486109],"iteration":163,"passed_time":0.3597571069,"remaining_time":1.833883789},
{"learn":[0.09847799036],"iteration":164,"passed_time":0.3616744436,"remaining_time":1.830291881},
{"learn":[0.09830871927],"iteration":165,"passed_time":0.3632005381,"remaining_time":1.824754511},
{"learn":[0.09813286266],"iteration":166,"passed_time":0.3646448843,"remaining_time":1.818857417},
{"learn":[0.09797449959],"iteration":167,"passed_time":0.3663464753,"remaining_time":1.814287306},
{"learn":[0.09772400476],"iteration":168,"passed_time":0.3677370308,"remaining_time":1.808221732},
{"learn":[0.09750742462],"iteration":169,"passed_time":0.3696910751,"remaining_time":1.804962308},
{"learn":[0.09730512608],"iteration":170,"passed_time":0.3744130642,"remaining_time":1.815137019},
{"learn":[0.09715238725],"iteration":171,"passed_time":0.3763608586,"remaining_time":1.811783668},
{"learn":[0.0969110597],"iteration":172,"passed_time":0.377792205,"remaining_time":1.805977766},
{"learn":[0.09666915365],"iteration":173,"passed_time":0.3790454717,"remaining_time":1.799376779},
{"learn":[0.09652933094],"iteration":174,"passed_time":0.3803640703,"remaining_time":1.793144903},
{"learn":[0.09640017253],"iteration":175,"passed_time":0.3829601851,"remaining_time":1.792949958},
{"learn":[0.09615990899],"iteration":176,"passed_time":0.3845077376,"remaining_time":1.787852362},
{"learn":[0.0959545466],"iteration":177,"passed_time":0.385906293,"remaining_time":1.782106589},
{"learn":[0.09566208747],"iteration":178,"passed_time":0.3873669305,"remaining_time":1.776694134},
{"learn":[0.09549513621],"iteration":179,"passed_time":0.3891475616,"remaining_time":1.772783336},
{"learn":[0.09528756075],"iteration":180,"passed_time":0.3907263634,"remaining_time":1.767982827},
{"learn":[0.0950855649],"iteration":181,"passed_time":0.3935898895,"remaining_time":1.768991921},
{"learn":[0.09494670783],"iteration":182,"passed_time":0.396403625,"remaining_time":1.769736402},
{"learn":[0.09468469796],"iteration":183,"passed_time":0.3979565523,"remaining_time":1.764850797},
{"learn":[0.09448862109],"iteration":184,"passed_time":0.4003194635,"remaining_time":1.763569528},
{"learn":[0.09420524664],"iteration":185,"passed_time":0.4017452683,"remaining_time":1.758175529},
{"learn":[0.09404798497],"iteration":186,"passed_time":0.4033163203,"remaining_time":1.753455446},
{"learn":[0.09378643969],"iteration":187,"passed_time":0.4050924098,"remaining_time":1.749654451},
{"learn":[0.09358737498],"iteration":188,"passed_time":0.4075022367,"remaining_time":1.748594254},
{"learn":[0.09345239076],"iteration":189,"passed_time":0.4086984628,"remaining_time":1.742346078},
{"learn":[0.09323894013],"iteration":190,"passed_time":0.4099963952,"remaining_time":1.73658159},
{"learn":[0.09301385798],"iteration":191,"passed_time":0.4120387294,"remaining_time":1.73399632},
{"learn":[0.0928017559],"iteration":192,"passed_time":0.4135316996,"remaining_time":1.729119594},
{"learn":[0.0925827108],"iteration":193,"passed_time":0.414945713,"remaining_time":1.723949715},
{"learn":[0.0924239304],"iteration":194,"passed_time":0.4165174733,"remaining_time":1.719469569},
{"learn":[0.09220293423],"iteration":195,"passed_time":0.4185106418,"remaining_time":1.716747735},
{"learn":[0.09203934805],"iteration":196,"passed_time":0.4201444009,"remaining_time":1.712568294},
{"learn":[0.0918714418],"iteration":197,"passed_time":0.4221520274,"remaining_time":1.709928919},
{"learn":[0.09167348637],"iteration":198,"passed_time":0.4234573347,"remaining_time":1.70446897},
{"learn":[0.09148993188],"iteration":199,"passed_time":0.4249931374,"remaining_time":1.699972549},
{"learn":[0.09130634557],"iteration":200,"passed_time":0.4262973613,"remaining_time":1.694585033},
{"learn":[0.09114752623],"iteration":201,"passed_time":0.4305481514,"remaining_time":1.700878341},
{"learn":[0.09092353819],"iteration":202,"passed_time":0.4333115546,"remaining_time":1.701228123},
{"learn":[0.0907377385],"iteration":203,"passed_time":0.4362001219,"remaining_time":1.70203577},
{"learn":[0.09056574314],"iteration":204,"passed_time":0.4378547555,"remaining_time":1.698022101},
{"learn":[0.09039438764],"iteration":205,"passed_time":0.4402207499,"remaining_time":1.696773182},
{"learn":[0.0902375894],"iteration":206,"passed_time":0.4416974704,"remaining_time":1.692106735},
{"learn":[0.09009586239],"iteration":207,"passed_time":0.4429939029,"remaining_time":1.686784476},
{"learn":[0.08991560169],"iteration":208,"passed_time":0.4445320388,"remaining_time":1.682415515},
{"learn":[0.08973681229],"iteration":209,"passed_time":0.4459133862,"remaining_time":1.677483691},
{"learn":[0.08955053086],"iteration":210,"passed_time":0.4473191915,"remaining_time":1.672676977},
{"learn":[0.08938451469],"iteration":211,"passed_time":0.449397025,"remaining_time":1.670400263},
{"learn":[0.08924409723],"iteration":212,"passed_time":0.451364194,"remaining_time":1.667716529},
{"learn":[0.08906878328],"iteration":213,"passed_time":0.4526359186,"remaining_time":1.662485196},
{"learn":[0.08887607601],"iteration":214,"passed_time":0.4571127876,"remaining_time":1.668993201},
{"learn":[0.08872413258],"iteration":215,"passed_time":0.458377804,"remaining_time":1.663741659},
{"learn":[0.0886256157],"iteration":216,"passed_time":0.4598071504,"remaining_time":1.65911981},
{"learn":[0.08847030967],"iteration":217,"passed_time":0.461295204,"remaining_time":1.654737842},
{"learn":[0.088293923],"iteration":218,"passed_time":0.4634138284,"remaining_time":1.65263105},
{"learn":[0.08816034427],"iteration":219,"passed_time":0.4655124531,"remaining_time":1.650453243},
{"learn":[0.08798250269],"iteration":220,"passed_time":0.468826137,"remaining_time":1.652559098},
{"learn":[0.08778611],"iteration":221,"passed_time":0.470374856,"remaining_time":1.648430802},
{"learn":[0.08764998166],"iteration":222,"passed_time":0.4723584831,"remaining_time":1.645840993},
{"learn":[0.08752307146],"iteration":223,"passed_time":0.4743428601,"remaining_time":1.643259194},
{"learn":[0.08739177981],"iteration":224,"passed_time":0.477453423,"remaining_time":1.64456179},
{"learn":[0.08726607472],"iteration":225,"passed_time":0.479503882,"remaining_time":1.642194711},
{"learn":[0.08720450334],"iteration":226,"passed_time":0.4889433185,"remaining_time":1.664992005},
{"learn":[0.08705517089],"iteration":227,"passed_time":0.4906945336,"remaining_time":1.661474473},
{"learn":[0.08697409191],"iteration":228,"passed_time":0.4928827815,"remaining_time":1.659443775},
{"learn":[0.08689575002],"iteration":229,"passed_time":0.4946366215,"remaining_time":1.655957385},
{"learn":[0.08671265285],"iteration":230,"passed_time":0.4962282147,"remaining_time":1.651945875},
{"learn":[0.08661051062],"iteration":231,"passed_time":0.4992572375,"remaining_time":1.652713614},
{"learn":[0.08647830343],"iteration":232,"passed_time":0.5010726596,"remaining_time":1.649453777},
{"learn":[0.08634863192],"iteration":233,"passed_time":0.5030154958,"remaining_time":1.646623375},
{"learn":[0.08620107014],"iteration":234,"passed_time":0.5041536814,"remaining_time":1.641181133},
{"learn":[0.08610514729],"iteration":235,"passed_time":0.5061465166,"remaining_time":1.638542113},
{"learn":[0.0859642092],"iteration":236,"passed_time":0.5078448577,"remaining_time":1.634960449},
{"learn":[0.08585841828],"iteration":237,"passed_time":0.509130707,"remaining_time":1.630073944},
{"learn":[0.0856923075],"iteration":238,"passed_time":0.5103954734,"remaining_time":1.625150441},
{"learn":[0.08556379067],"iteration":239,"passed_time":0.5117229469,"remaining_time":1.620455999},
{"learn":[0.08547677607],"iteration":240,"passed_time":0.5130935862,"remaining_time":1.615925444},
{"learn":[0.08533545083],"iteration":241,"passed_time":0.5143867687,"remaining_time":1.611178391},
{"learn":[0.08522264191],"iteration":242,"passed_time":0.51565666,"remaining_time":1.606387208},
{"learn":[0.08510857927],"iteration":243,"passed_time":0.5172370451,"remaining_time":1.60258691},
{"learn":[0.08499430709],"iteration":244,"passed_time":0.51841198,"remaining_time":1.597555285},
{"learn":[0.08477431013],"iteration":245,"passed_time":0.5203006506,"remaining_time":1.594742645},
{"learn":[0.08461635088],"iteration":246,"passed_time":0.5223688176,"remaining_time":1.592484695},
{"learn":[0.08445978123],"iteration":247,"passed_time":0.5236976661,"remaining_time":1.587986471},
{"learn":[0.08435922256],"iteration":248,"passed_time":0.5249647658,"remaining_time":1.583327466},
{"learn":[0.08419122109],"iteration":249,"passed_time":0.5264163618,"remaining_time":1.579249085},
{"learn":[0.08400410809],"iteration":250,"passed_time":0.5277765846,"remaining_time":1.574918972},
{"learn":[0.08382217007],"iteration":251,"passed_time":0.5294408014,"remaining_time":1.57151476},
{"learn":[0.08364754953],"iteration":252,"passed_time":0.5310978516,"remaining_time":1.568103143},
{"learn":[0.08349298151],"iteration":253,"passed_time":0.5325414478,"remaining_time":1.564078425},
{"learn":[0.0833269721],"iteration":254,"passed_time":0.533700258,"remaining_time":1.55924193},
{"learn":[0.08315978097],"iteration":255,"passed_time":0.5351187713,"remaining_time":1.555188929},
{"learn":[0.08301152507],"iteration":256,"passed_time":0.5365499511,"remaining_time":1.551193049},
{"learn":[0.08282865569],"iteration":257,"passed_time":0.5378601749,"remaining_time":1.546869185},
{"learn":[0.08270169059],"iteration":258,"passed_time":0.5391342745,"remaining_time":1.542465241},
{"learn":[0.08253076553],"iteration":259,"passed_time":0.5408471986,"remaining_time":1.539334335},
{"learn":[0.08247900846],"iteration":260,"passed_time":0.5425037905,"remaining_time":1.536054794},
{"learn":[0.08245133575],"iteration":261,"passed_time":0.5442365059,"remaining_time":1.533002066},
{"learn":[0.08228000826],"iteration":262,"passed_time":0.5457974747,"remaining_time":1.529478095},
{"learn":[0.0821590925],"iteration":263,"passed_time":0.5478145595,"remaining_time":1.52724059},
{"learn":[0.08209135704],"iteration":264,"passed_time":0.5494401103,"remaining_time":1.523918797},
{"learn":[0.08193334962],"iteration":265,"passed_time":0.5517483559,"remaining_time":1.522493584},
{"learn":[0.08180861783],"iteration":266,"passed_time":0.5536207768,"remaining_time":1.519865279},
{"learn":[0.08166521469],"iteration":267,"passed_time":0.5550194572,"remaining_time":1.515948667},
{"learn":[0.08159849918],"iteration":268,"passed_time":0.5575736979,"remaining_time":1.515190978},
{"learn":[0.08147510072],"iteration":269,"passed_time":0.5608034251,"remaining_time":1.516246297},
{"learn":[0.08135500151],"iteration":270,"passed_time":0.5639648619,"remaining_time":1.517086289},
{"learn":[0.0811845344],"iteration":271,"passed_time":0.5658338663,"remaining_time":1.514437701},
{"learn":[0.08099389971],"iteration":272,"passed_time":0.5679557822,"remaining_time":1.512468328},
{"learn":[0.0808513059],"iteration":273,"passed_time":0.5698559526,"remaining_time":1.509910298},
{"learn":[0.08077906015],"iteration":274,"passed_time":0.5722792375,"remaining_time":1.508736172},
{"learn":[0.08066754255],"iteration":275,"passed_time":0.5736896677,"remaining_time":1.504896085},
{"learn":[0.08055762781],"iteration":276,"passed_time":0.5767135656,"remaining_time":1.505284866},
{"learn":[0.08040807706],"iteration":277,"passed_time":0.5784354896,"remaining_time":1.50226771},
{"learn":[0.08029014477],"iteration":278,"passed_time":0.5798622528,"remaining_time":1.498497076},
{"learn":[0.0801548562],"iteration":279,"passed_time":0.5812768912,"remaining_time":1.494712006},
{"learn":[0.08004570672],"iteration":280,"passed_time":0.5827739446,"remaining_time":1.491154684},
{"learn":[0.07992419907],"iteration":281,"passed_time":0.5840429609,"remaining_time":1.487031369},
{"learn":[0.0797988365],"iteration":282,"passed_time":0.5853744343,"remaining_time":1.483086464},
{"learn":[0.07971618003],"iteration":283,"passed_time":0.5876195145,"remaining_time":1.481463283},
{"learn":[0.07955716105],"iteration":284,"passed_time":0.5890051118,"remaining_time":1.477679491},
{"learn":[0.079386312],"iteration":285,"passed_time":0.5902628784,"remaining_time":1.47359334},
{"learn":[0.07931763231],"iteration":286,"passed_time":0.5916913915,"remaining_time":1.469951088},
{"learn":[0.07923373402],"iteration":287,"passed_time":0.5930763639,"remaining_time":1.466216566},
{"learn":[0.07910570232],"iteration":288,"passed_time":0.5944516697,"remaining_time":1.462474523},
{"learn":[0.07902291997],"iteration":289,"passed_time":0.5958094759,"remaining_time":1.458705958},
{"learn":[0.07887621985],"iteration":290,"passed_time":0.5971378244,"remaining_time":1.454882191},
{"learn":[0.07874749786],"iteration":291,"passed_time":0.5989344135,"remaining_time":1.452210838},
{"learn":[0.07860685525],"iteration":292,"passed_time":0.6005107987,"remaining_time":1.449014112},
{"learn":[0.07846839283],"iteration":293,"passed_time":0.602434302,"remaining_time":1.446661963},
{"learn":[0.07842416675],"iteration":294,"passed_time":0.6038755649,"remaining_time":1.443160248},
{"learn":[0.078295048],"iteration":295,"passed_time":0.605168289,"remaining_time":1.439319174},
{"learn":[0.07818956003],"iteration":296,"passed_time":0.606471513,"remaining_time":1.435520113},
{"learn":[0.07805880813],"iteration":297,"passed_time":0.6079503168,"remaining_time":1.432151417},
{"learn":[0.07795112861],"iteration":298,"passed_time":0.609444037,"remaining_time":1.428830334},
{"learn":[0.07786377328],"iteration":299,"passed_time":0.6115653279,"remaining_time":1.426985765},
{"learn":[0.07774293394],"iteration":300,"passed_time":0.6135718712,"remaining_time":1.424872884},
{"learn":[0.07766471187],"iteration":301,"passed_time":0.61538671,"remaining_time":1.422317628},
{"learn":[0.07753303595],"iteration":302,"passed_time":0.6173462958,"remaining_time":1.420100225},
{"learn":[0.07746260383],"iteration":303,"passed_time":0.6187202267,"remaining_time":1.416543677},
{"learn":[0.07731659871],"iteration":304,"passed_time":0.6201706978,"remaining_time":1.413175852},
{"learn":[0.07719022849],"iteration":305,"passed_time":0.6223305296,"remaining_time":1.411429371},
{"learn":[0.07707202542],"iteration":306,"passed_time":0.6242762408,"remaining_time":1.409196856},
{"learn":[0.07695314917],"iteration":307,"passed_time":0.6257075038,"remaining_time":1.405810366},
{"learn":[0.07686765288],"iteration":308,"passed_time":0.6271298921,"remaining_time":1.402416684},
{"learn":[0.0767810225],"iteration":309,"passed_time":0.6284230329,"remaining_time":1.398748041},
{"learn":[0.07659990348],"iteration":310,"passed_time":0.6297817975,"remaining_time":1.395240059},
{"learn":[0.0764538959],"iteration":311,"passed_time":0.6312269353,"remaining_time":1.391936319},
{"learn":[0.07634721501],"iteration":312,"passed_time":0.6340535455,"remaining_time":1.391676632},
{"learn":[0.0762218502],"iteration":313,"passed_time":0.6360763801,"remaining_time":1.389644576},
{"learn":[0.07608702952],"iteration":314,"passed_time":0.6376718066,"remaining_time":1.386683135},
{"learn":[0.07598396447],"iteration":315,"passed_time":0.6389904469,"remaining_time":1.383131221},
{"learn":[0.07580399952],"iteration":316,"passed_time":0.6404311681,"remaining_time":1.379856428},
{"learn":[0.07574580421],"iteration":317,"passed_time":0.6417313088,"remaining_time":1.376291675},
{"learn":[0.07568325124],"iteration":318,"passed_time":0.64308949,"remaining_time":1.372865024},
{"learn":[0.07556136017],"iteration":319,"passed_time":0.6484114254,"remaining_time":1.377874279},
{"learn":[0.07547998312],"iteration":320,"passed_time":0.6498662714,"remaining_time":1.374639247},
{"learn":[0.07534567341],"iteration":321,"passed_time":0.6518423152,"remaining_time":1.372512701},
{"learn":[0.075221272],"iteration":322,"passed_time":0.6538336505,"remaining_time":1.370419137},
{"learn":[0.07514677263],"iteration":323,"passed_time":0.6552618719,"remaining_time":1.367151313},
{"learn":[0.0749859784],"iteration":324,"passed_time":0.6569858792,"remaining_time":1.364509134},
{"learn":[0.07486608877],"iteration":325,"passed_time":0.6589919641,"remaining_time":1.362455779},
{"learn":[0.07478960516],"iteration":326,"passed_time":0.6602700219,"remaining_time":1.358904357},
{"learn":[0.07469698695],"iteration":327,"passed_time":0.6615983704,"remaining_time":1.355469832},
{"learn":[0.07462536064],"iteration":328,"passed_time":0.663134548,"remaining_time":1.352471981},
{"learn":[0.07456352531],"iteration":329,"passed_time":0.6645529781,"remaining_time":1.349243925},
{"learn":[0.07447614166],"iteration":330,"passed_time":0.6657569957,"remaining_time":1.345593444},
{"learn":[0.07436928478],"iteration":331,"passed_time":0.6673744217,"remaining_time":1.342789499},
{"learn":[0.0742719276],"iteration":332,"passed_time":0.6700260771,"remaining_time":1.342064244},
{"learn":[0.07414935469],"iteration":333,"passed_time":0.671416216,"remaining_time":1.338811976},
{"learn":[0.07402251519],"iteration":334,"passed_time":0.6727369813,"remaining_time":1.335433112},
{"learn":[0.07389124066],"iteration":335,"passed_time":0.6742409929,"remaining_time":1.332428629},
{"learn":[0.07378188847],"iteration":336,"passed_time":0.6757666291,"remaining_time":1.329475594},
{"learn":[0.07363040043],"iteration":337,"passed_time":0.6778610456,"remaining_time":1.327645006},
{"learn":[0.07349701966],"iteration":338,"passed_time":0.6792429763,"remaining_time":1.324423621},
{"learn":[0.07338384807],"iteration":339,"passed_time":0.6806809476,"remaining_time":1.32132184},
{"learn":[0.07332631317],"iteration":340,"passed_time":0.6820677533,"remaining_time":1.318130937},
{"learn":[0.07320922482],"iteration":341,"passed_time":0.6833436444,"remaining_time":1.314737187},
{"learn":[0.07312990574],"iteration":342,"passed_time":0.6846921592,"remaining_time":1.311494894},
{"learn":[0.0729912785],"iteration":343,"passed_time":0.6859462591,"remaining_time":1.308083564},
{"learn":[0.07283776548],"iteration":344,"passed_time":0.6877088906,"remaining_time":1.305650213},
{"learn":[0.07273345831],"iteration":345,"passed_time":0.6894447726,"remaining_time":1.303170177},
{"learn":[0.0726367279],"iteration":346,"passed_time":0.6909014102,"remaining_time":1.300168936},
{"learn":[0.07248862585],"iteration":347,"passed_time":0.6925158779,"remaining_time":1.297472277},
{"learn":[0.07237854895],"iteration":348,"passed_time":0.6938257684,"remaining_time":1.294213683},
{"learn":[0.07224421201],"iteration":349,"passed_time":0.6952787811,"remaining_time":1.291232022},
{"learn":[0.07216444804],"iteration":350,"passed_time":0.6972388253,"remaining_time":1.289196574},
{"learn":[0.07212352588],"iteration":351,"passed_time":0.6996573603,"remaining_time":1.288005595},
{"learn":[0.07204911206],"iteration":352,"passed_time":0.7010851651,"remaining_time":1.28499179},
{"learn":[0.07193230068],"iteration":353,"passed_time":0.7024760957,"remaining_time":1.281919655},
{"learn":[0.0718354619],"iteration":354,"passed_time":0.7038810676,"remaining_time":1.278882503},
{"learn":[0.07173458581],"iteration":355,"passed_time":0.7052693732,"remaining_time":1.275824372},
{"learn":[0.07163980583],"iteration":356,"passed_time":0.7066910948,"remaining_time":1.272835781},
{"learn":[0.07152302394],"iteration":357,"passed_time":0.7080200683,"remaining_time":1.26968962},
{"learn":[0.07141226944],"iteration":358,"passed_time":0.7100928186,"remaining_time":1.267881606},
{"learn":[0.07132729724],"iteration":359,"passed_time":0.7123638565,"remaining_time":1.266424634},
{"learn":[0.07123687317],"iteration":360,"passed_time":0.7135504578,"remaining_time":1.263043608},
{"learn":[0.07115012389],"iteration":361,"passed_time":0.7149979289,"remaining_time":1.260134471},
{"learn":[0.07109401294],"iteration":362,"passed_time":0.71636336,"remaining_time":1.257089422},
{"learn":[0.07098680784],"iteration":363,"passed_time":0.7177059582,"remaining_time":1.254013707},
{"learn":[0.07089118558],"iteration":364,"passed_time":0.719401091,"remaining_time":1.251560802},
{"learn":[0.07082326061],"iteration":365,"passed_time":0.7217251696,"remaining_time":1.250201523},
{"learn":[0.07069600921],"iteration":366,"passed_time":0.7234614682,"remaining_time":1.247823186},
{"learn":[0.07064600822],"iteration":367,"passed_time":0.7248517738,"remaining_time":1.244854133},
{"learn":[0.07060678044],"iteration":368,"passed_time":0.7262695788,"remaining_time":1.241940662},
{"learn":[0.07051804169],"iteration":369,"passed_time":0.7278375892,"remaining_time":1.23929103},
{"learn":[0.07047924169],"iteration":370,"passed_time":0.7290770644,"remaining_time":1.236090225},
{"learn":[0.07036160545],"iteration":371,"passed_time":0.7305487434,"remaining_time":1.233291965},
{"learn":[0.07021368893],"iteration":372,"passed_time":0.7319268825,"remaining_time":1.23034358},
{"learn":[0.07013871999],"iteration":373,"passed_time":0.7337824288,"remaining_time":1.228202675},
{"learn":[0.07004897719],"iteration":374,"passed_time":0.7351949422,"remaining_time":1.225324904},
{"learn":[0.07002060408],"iteration":375,"passed_time":0.7366634129,"remaining_time":1.222547792},
{"learn":[0.06998428189],"iteration":376,"passed_time":0.7379754284,"remaining_time":1.219519077},
{"learn":[0.06993171374],"iteration":377,"passed_time":0.7393913168,"remaining_time":1.216670368},
{"learn":[0.0697897852],"iteration":378,"passed_time":0.7408539959,"remaining_time":1.213905888},
{"learn":[0.06965287638],"iteration":379,"passed_time":0.7422488847,"remaining_time":1.211037654},
{"learn":[0.06949223915],"iteration":380,"passed_time":0.7437276885,"remaining_time":1.208313489},
{"learn":[0.06937075349],"iteration":381,"passed_time":0.7457986471,"remaining_time":1.206553832},
{"learn":[0.06933725494],"iteration":382,"passed_time":0.7470759966,"remaining_time":1.203514073},
{"learn":[0.06916600011],"iteration":383,"passed_time":0.7484172615,"remaining_time":1.200586024},
{"learn":[0.06905238684],"iteration":384,"passed_time":0.7498475663,"remaining_time":1.19780845},
{"learn":[0.06895055056],"iteration":385,"passed_time":0.7519566908,"remaining_time":1.196117638},
{"learn":[0.06883371081],"iteration":386,"passed_time":0.7533236219,"remaining_time":1.193249044},
{"learn":[0.06876262734],"iteration":387,"passed_time":0.7546608868,"remaining_time":1.190341399},
{"learn":[0.06866132331],"iteration":388,"passed_time":0.7567657198,"remaining_time":1.188647442},
{"learn":[0.06855432853],"iteration":389,"passed_time":0.758409562,"remaining_time":1.18623034},
{"learn":[0.06850020536],"iteration":390,"passed_time":0.7597386604,"remaining_time":1.183326967},
{"learn":[0.06838573995],"iteration":391,"passed_time":0.7612159642,"remaining_time":1.180661496},
{"learn":[0.06831576044],"iteration":392,"passed_time":0.7624982303,"remaining_time":1.177700829},
{"learn":[0.06821397675],"iteration":393,"passed_time":0.7639099521,"remaining_time":1.174947794},
{"learn":[0.06814022229],"iteration":394,"passed_time":0.7652193843,"remaining_time":1.17204488},
{"learn":[0.06803158075],"iteration":395,"passed_time":0.7664769425,"remaining_time":1.169070892},
{"learn":[0.06792489963],"iteration":396,"passed_time":0.7685735256,"remaining_time":1.167379939},
{"learn":[0.06781871689],"iteration":397,"passed_time":0.7705099453,"remaining_time":1.165444691},
{"learn":[0.06772884804],"iteration":398,"passed_time":0.7719978739,"remaining_time":1.16283389},
{"learn":[0.06759840359],"iteration":399,"passed_time":0.7733610967,"remaining_time":1.160041645},
{"learn":[0.06747026011],"iteration":400,"passed_time":0.7747073615,"remaining_time":1.157231196},
{"learn":[0.06735828327],"iteration":401,"passed_time":0.7768450688,"remaining_time":1.155605351},
{"learn":[0.06722518948],"iteration":402,"passed_time":0.7783619135,"remaining_time":1.153057227},
{"learn":[0.0671544595],"iteration":403,"passed_time":0.779722928,"remaining_time":1.150284319},
{"learn":[0.06709359348],"iteration":404,"passed_time":0.7814460186,"remaining_time":1.148050324},
{"learn":[0.0669907123],"iteration":405,"passed_time":0.7829212808,"remaining_time":1.145456258},
{"learn":[0.06691662581],"iteration":406,"passed_time":0.7844082094,"remaining_time":1.142884688},
{"learn":[0.06684403606],"iteration":407,"passed_time":0.7864907511,"remaining_time":1.141182659},
{"learn":[0.0667620582],"iteration":408,"passed_time":0.787780392,"remaining_time":1.138333036},
{"learn":[0.06662166179],"iteration":409,"passed_time":0.7892277381,"remaining_time":1.135717965},
{"learn":[0.06652324225],"iteration":410,"passed_time":0.7910276605,"remaining_time":1.133613849},
{"learn":[0.06642349679],"iteration":411,"passed_time":0.7925125475,"remaining_time":1.131061597},
{"learn":[0.06633132834],"iteration":412,"passed_time":0.7939187278,"remaining_time":1.128402647},
{"learn":[0.06624814072],"iteration":413,"passed_time":0.795295742,"remaining_time":1.125708466},
{"learn":[0.06618159171],"iteration":414,"passed_time":0.7968662939,"remaining_time":1.12329345},
{"learn":[0.06609548233],"iteration":415,"passed_time":0.7980794364,"remaining_time":1.120380747},
{"learn":[0.06602936286],"iteration":416,"passed_time":0.7995449488,"remaining_time":1.117829029},
{"learn":[0.06596166513],"iteration":417,"passed_time":0.8014305778,"remaining_time":1.115867455},
{"learn":[0.0658976964],"iteration":418,"passed_time":0.8029377143,"remaining_time":1.113381413},
{"learn":[0.06578535524],"iteration":419,"passed_time":0.8045150162,"remaining_time":1.110996927},
{"learn":[0.06566711039],"iteration":420,"passed_time":0.8060484439,"remaining_time":1.108555936},
{"learn":[0.06560855462],"iteration":421,"passed_time":0.8073348349,"remaining_time":1.105780888},
{"learn":[0.06553543919],"iteration":422,"passed_time":0.8092617547,"remaining_time":1.103886602},
{"learn":[0.06545035897],"iteration":423,"passed_time":0.8107554749,"remaining_time":1.101403664},
{"learn":[0.06535169309],"iteration":424,"passed_time":0.8121512803,"remaining_time":1.098792909},
{"learn":[0.06527981853],"iteration":425,"passed_time":0.8140262429,"remaining_time":1.096833482},
{"learn":[0.06525164074],"iteration":426,"passed_time":0.8165673588,"remaining_time":1.095768376},
{"learn":[0.06516867197],"iteration":427,"passed_time":0.8179147069,"remaining_time":1.093100963},
{"learn":[0.06506012035],"iteration":428,"passed_time":0.8192523885,"remaining_time":1.090426839},
{"learn":[0.06501333327],"iteration":429,"passed_time":0.820561529,"remaining_time":1.087721097},
{"learn":[0.06496072319],"iteration":430,"passed_time":0.8220287914,"remaining_time":1.085230585},
{"learn":[0.06490518495],"iteration":431,"passed_time":0.8242011647,"remaining_time":1.083671902},
{"learn":[0.06484837341],"iteration":432,"passed_time":0.8275548894,"remaining_time":1.083657326},
{"learn":[0.06477251652],"iteration":433,"passed_time":0.829089817,"remaining_time":1.081255384},
{"learn":[0.06470052948],"iteration":434,"passed_time":0.8305032472,"remaining_time":1.07869962},
{"learn":[0.06460209643],"iteration":435,"passed_time":0.8319116357,"remaining_time":1.076142575},
{"learn":[0.06450064094],"iteration":436,"passed_time":0.8332271094,"remaining_time":1.073471081},
{"learn":[0.06440660665],"iteration":437,"passed_time":0.8348236609,"remaining_time":1.071166432},
{"learn":[0.06429156362],"iteration":438,"passed_time":0.8367262895,"remaining_time":1.069256147},
{"learn":[0.06421505985],"iteration":439,"passed_time":0.8386304598,"remaining_time":1.067347858},
{"learn":[0.06414124618],"iteration":440,"passed_time":0.8402505942,"remaining_time":1.065079551},
{"learn":[0.0640736625],"iteration":441,"passed_time":0.8417501892,"remaining_time":1.062662004},
{"learn":[0.06397809368],"iteration":442,"passed_time":0.8432031185,"remaining_time":1.060189926},
{"learn":[0.06389848978],"iteration":443,"passed_time":0.8446582145,"remaining_time":1.057725151},
{"learn":[0.06381568082],"iteration":444,"passed_time":0.8460221039,"remaining_time":1.055151163},
{"learn":[0.06371888185],"iteration":445,"passed_time":0.8503270179,"remaining_time":1.056235803},
{"learn":[0.06367049034],"iteration":446,"passed_time":0.8515969926,"remaining_time":1.053541693},
{"learn":[0.06359650808],"iteration":447,"passed_time":0.8530212974,"remaining_time":1.051044099},
{"learn":[0.06350189589],"iteration":448,"passed_time":0.854628682,"remaining_time":1.048775955},
{"learn":[0.06341809163],"iteration":449,"passed_time":0.8561349019,"remaining_time":1.046387102},
{"learn":[0.06335489916],"iteration":450,"passed_time":0.8574866666,"remaining_time":1.043814146},
{"learn":[0.06329012786],"iteration":451,"passed_time":0.8587538913,"remaining_time":1.041144098},
{"learn":[0.06317706515],"iteration":452,"passed_time":0.8613503811,"remaining_time":1.040085339},
{"learn":[0.06310418196],"iteration":453,"passed_time":0.8629156415,"remaining_time":1.037779604},
{"learn":[0.06297234395],"iteration":454,"passed_time":0.8645395674,"remaining_time":1.035547394},
{"learn":[0.06289159076],"iteration":455,"passed_time":0.8666818996,"remaining_time":1.033936301},
{"learn":[0.06280362331],"iteration":456,"passed_time":0.8681696616,"remaining_time":1.031545134},
{"learn":[0.06275793241],"iteration":457,"passed_time":0.8697470051,"remaining_time":1.029263923},
{"learn":[0.06269305671],"iteration":458,"passed_time":0.8728133605,"remaining_time":1.028740802},
{"learn":[0.06263187932],"iteration":459,"passed_time":0.8744611609,"remaining_time":1.026541363},
{"learn":[0.06251582197],"iteration":460,"passed_time":0.876027338,"remaining_time":1.024248883},
{"learn":[0.06246711158],"iteration":461,"passed_time":0.8772566051,"remaining_time":1.021567215},
{"learn":[0.06237916343],"iteration":462,"passed_time":0.8785544125,"remaining_time":1.018971316},
{"learn":[0.06231365584],"iteration":463,"passed_time":0.8800779238,"remaining_time":1.01664174},
{"learn":[0.06226791414],"iteration":464,"passed_time":0.8853460269,"remaining_time":1.018623923},
{"learn":[0.06216999863],"iteration":465,"passed_time":0.8873807779,"remaining_time":1.016869818},
{"learn":[0.06207882066],"iteration":466,"passed_time":0.8895682342,"remaining_time":1.015288798},
{"learn":[0.0620681834],"iteration":467,"passed_time":0.8929992074,"remaining_time":1.015118757},
{"learn":[0.06200292175],"iteration":468,"passed_time":0.8957728603,"remaining_time":1.014190595},
{"learn":[0.06189684185],"iteration":469,"passed_time":0.8978001948,"remaining_time":1.012412986},
{"learn":[0.06182914585],"iteration":470,"passed_time":0.9012541675,"remaining_time":1.012236634},
{"learn":[0.06172202704],"iteration":471,"passed_time":0.9026689309,"remaining_time":1.009765245},
{"learn":[0.06163794256],"iteration":472,"passed_time":0.904249691,"remaining_time":1.007483271},
{"learn":[0.06154786895],"iteration":473,"passed_time":0.9068981798,"remaining_time":1.006389119},
{"learn":[0.06146615891],"iteration":474,"passed_time":0.9093368811,"remaining_time":1.005056553},
{"learn":[0.06139334779],"iteration":475,"passed_time":0.9118317479,"remaining_time":1.003781168},
{"learn":[0.06134156595],"iteration":476,"passed_time":0.9139921214,"remaining_time":1.002133919},
{"learn":[0.06125240169],"iteration":477,"passed_time":0.9153721355,"remaining_time":0.9996323321},
{"learn":[0.06115368732],"iteration":478,"passed_time":0.9167760658,"remaining_time":0.9971614411},
{"learn":[0.06107920497],"iteration":479,"passed_time":0.9186949025,"remaining_time":0.9952528111},
{"learn":[0.06099856874],"iteration":480,"passed_time":0.9200710417,"remaining_time":0.9927585668},
{"learn":[0.06096442018],"iteration":481,"passed_time":0.9214058067,"remaining_time":0.9902244977},
{"learn":[0.06086560576],"iteration":482,"passed_time":0.9233531012,"remaining_time":0.988351042},
{"learn":[0.0607624868],"iteration":483,"passed_time":0.9247077824,"remaining_time":0.9858454871},
{"learn":[0.06070307254],"iteration":484,"passed_time":0.9269551542,"remaining_time":0.9842925864},
{"learn":[0.06064615023],"iteration":485,"passed_time":0.928403792,"remaining_time":0.9818920763},
{"learn":[0.06062585664],"iteration":486,"passed_time":0.931737892,"remaining_time":0.9814815988},
{"learn":[0.06057731318],"iteration":487,"passed_time":0.9332086543,"remaining_time":0.9791041619},
{"learn":[0.06052828028],"iteration":488,"passed_time":0.9353176955,"remaining_time":0.9773974283},
{"learn":[0.06048978036],"iteration":489,"passed_time":0.9389972471,"remaining_time":0.9773236653},
{"learn":[0.06040805361],"iteration":490,"passed_time":0.9426596323,"remaining_time":0.9772174192},
{"learn":[0.06031041632],"iteration":491,"passed_time":0.9465116803,"remaining_time":0.977292548},
{"learn":[0.06021602746],"iteration":492,"passed_time":0.9556919136,"remaining_time":0.9828312378},
{"learn":[0.06012516123],"iteration":493,"passed_time":0.9599905361,"remaining_time":0.9833101443},
{"learn":[0.06005305521],"iteration":494,"passed_time":0.9620971607,"remaining_time":0.981533467},
{"learn":[0.05998395913],"iteration":495,"passed_time":0.9647551076,"remaining_time":0.9803156739},
{"learn":[0.05992946675],"iteration":496,"passed_time":0.9670713531,"remaining_time":0.9787462587},
{"learn":[0.05988414457],"iteration":497,"passed_time":0.9686086973,"remaining_time":0.9763886869},
{"learn":[0.05981927241],"iteration":498,"passed_time":0.971382517,"remaining_time":0.9752758337},
{"learn":[0.05974939668],"iteration":499,"passed_time":0.9730211926,"remaining_time":0.9730211926},
{"learn":[0.05966899008],"iteration":500,"passed_time":0.9757724293,"remaining_time":0.9718771302},
{"learn":[0.05962221002],"iteration":501,"passed_time":0.9773436479,"remaining_time":0.9695560491},
{"learn":[0.0595395536],"iteration":502,"passed_time":0.9789474909,"remaining_time":0.9672701848},
{"learn":[0.05950021588],"iteration":503,"passed_time":0.9805305426,"remaining_time":0.9649665657},
{"learn":[0.0594343735],"iteration":504,"passed_time":0.9820477623,"remaining_time":0.9626012719},
{"learn":[0.05941765701],"iteration":505,"passed_time":0.9834011519,"remaining_time":0.9600793855},
{"learn":[0.05932425031],"iteration":506,"passed_time":0.9848388732,"remaining_time":0.9576441114},
{"learn":[0.05920794503],"iteration":507,"passed_time":0.9885204664,"remaining_time":0.9573859635},
{"learn":[0.05914874048],"iteration":508,"passed_time":0.9902369737,"remaining_time":0.9552187703},
{"learn":[0.05907745264],"iteration":509,"passed_time":0.9919517312,"remaining_time":0.9530516633},
{"learn":[0.05899235558],"iteration":510,"passed_time":0.9933765777,"remaining_time":0.9506088973},
{"learn":[0.05889425588],"iteration":511,"passed_time":0.9949685042,"remaining_time":0.9483293556},
{"learn":[0.05881447479],"iteration":512,"passed_time":0.9962799781,"remaining_time":0.945786256},
{"learn":[0.05879476081],"iteration":513,"passed_time":0.9977952811,"remaining_time":0.9434406744},
{"learn":[0.05871231008],"iteration":514,"passed_time":0.9992990011,"remaining_time":0.9410874088},
{"learn":[0.05866937728],"iteration":515,"passed_time":1.000810138,"remaining_time":0.9387443926},
{"learn":[0.05864362206],"iteration":516,"passed_time":1.002475229,"remaining_time":0.9365484251},
{"learn":[0.05855248531],"iteration":517,"passed_time":1.003810619,"remaining_time":0.9340477191},
{"learn":[0.05843961622],"iteration":518,"passed_time":1.005226133,"remaining_time":0.9316257608},
{"learn":[0.05838237482],"iteration":519,"passed_time":1.006981973,"remaining_time":0.9295218209},
{"learn":[0.05829433746],"iteration":520,"passed_time":1.008594565,"remaining_time":0.9272875179},
{"learn":[0.05819237346],"iteration":521,"passed_time":1.011128057,"remaining_time":0.9258988717},
{"learn":[0.05812262843],"iteration":522,"passed_time":1.012579861,"remaining_time":0.9235192995},
{"learn":[0.05809391687],"iteration":523,"passed_time":1.014165954,"remaining_time":0.9212652561},
{"learn":[0.05805225076],"iteration":524,"passed_time":1.015617759,"remaining_time":0.9188922577},
{"learn":[0.05800451726],"iteration":525,"passed_time":1.017218477,"remaining_time":0.9166569542},
{"learn":[0.05791249116],"iteration":526,"passed_time":1.018723488,"remaining_time":0.9143381592},
{"learn":[0.05783924775],"iteration":527,"passed_time":1.020179959,"remaining_time":0.9119790543},
{"learn":[0.05781727657],"iteration":528,"passed_time":1.02152889,"remaining_time":0.9095276133},
{"learn":[0.05775686754],"iteration":529,"passed_time":1.023549808,"remaining_time":0.9076762452},
{"learn":[0.05768313131],"iteration":530,"passed_time":1.02549077,"remaining_time":0.9057536177},
{"learn":[0.05763439859],"iteration":531,"passed_time":1.026795827,"remaining_time":0.9032715169},
{"learn":[0.05757629198],"iteration":532,"passed_time":1.02856475,"remaining_time":0.9012002593},
{"learn":[0.05755864016],"iteration":533,"passed_time":1.030084095,"remaining_time":0.8989123372},
{"learn":[0.05746240527],"iteration":534,"passed_time":1.031954891,"remaining_time":0.8969327554},
{"learn":[0.05741761754],"iteration":535,"passed_time":1.034614796,"remaining_time":0.8956366889},
{"learn":[0.05737474424],"iteration":536,"passed_time":1.036325803,"remaining_time":0.8935174058},
{"learn":[0.05731245527],"iteration":537,"passed_time":1.038127142,"remaining_time":0.8914772114},
{"learn":[0.05723365946],"iteration":538,"passed_time":1.039962939,"remaining_time":0.8894673745},
{"learn":[0.05718784521],"iteration":539,"passed_time":1.041541741,"remaining_time":0.8872392607},
{"learn":[0.05712370135],"iteration":540,"passed_time":1.043220707,"remaining_time":0.8850985298},
{"learn":[0.0570523229],"iteration":541,"passed_time":1.045623909,"remaining_time":0.8835714953},
{"learn":[0.05699809241],"iteration":542,"passed_time":1.047531704,"remaining_time":0.881624289},
{"learn":[0.05694791754],"iteration":543,"passed_time":1.049077215,"remaining_time":0.8793735481},
{"learn":[0.05687798889],"iteration":544,"passed_time":1.051300213,"remaining_time":0.8776910031},
{"learn":[0.05680173709],"iteration":545,"passed_time":1.052741684,"remaining_time":0.8753566382},
{"learn":[0.05670629299],"iteration":546,"passed_time":1.054791976,"remaining_time":0.8735297353},
{"learn":[0.05662885508],"iteration":547,"passed_time":1.058912477,"remaining_time":0.8734095615},
{"learn":[0.05656131533],"iteration":548,"passed_time":1.060593152,"remaining_time":0.8712705128},
{"learn":[0.0564759824],"iteration":549,"passed_time":1.062630028,"remaining_time":0.8694245683},
{"learn":[0.0564585154],"iteration":550,"passed_time":1.065067313,"remaining_time":0.8679042166},
{"learn":[0.05638434219],"iteration":551,"passed_time":1.067154729,"remaining_time":0.8660965919},
{"learn":[0.05633453596],"iteration":552,"passed_time":1.070656743,"remaining_time":0.8654313996},
{"learn":[0.05625505896],"iteration":553,"passed_time":1.072591787,"remaining_time":0.8634944714},
{"learn":[0.05616765394],"iteration":554,"passed_time":1.074417293,"remaining_time":0.8614697211},
{"learn":[0.05608878858],"iteration":555,"passed_time":1.076138425,"remaining_time":0.8593623393},
{"learn":[0.05602558777],"iteration":556,"passed_time":1.07796143,"remaining_time":0.8573373672},
{"learn":[0.05596821518],"iteration":557,"passed_time":1.080821831,"remaining_time":0.8561348556},
{"learn":[0.05592629661],"iteration":558,"passed_time":1.083411446,"remaining_time":0.8547127868},
{"learn":[0.05584442279],"iteration":559,"passed_time":1.085837273,"remaining_time":0.8531578572},
{"learn":[0.05577589338],"iteration":560,"passed_time":1.08841668,"remaining_time":0.8517200042},
{"learn":[0.05569894664],"iteration":561,"passed_time":1.092824342,"remaining_time":0.8517029566},
{"learn":[0.05561615246],"iteration":562,"passed_time":1.095721242,"remaining_time":0.8504976604},
{"learn":[0.05556307362],"iteration":563,"passed_time":1.098271024,"remaining_time":0.849018026},
{"learn":[0.05552513593],"iteration":564,"passed_time":1.100672935,"remaining_time":0.8474207552},
{"learn":[0.05547950175],"iteration":565,"passed_time":1.105938246,"remaining_time":0.8480162525},
{"learn":[0.05542649277],"iteration":566,"passed_time":1.108238909,"remaining_time":0.8463270679},
{"learn":[0.05535557831],"iteration":567,"passed_time":1.110220286,"remaining_time":0.8443928935},
{"learn":[0.05526465606],"iteration":568,"passed_time":1.111831545,"remaining_time":0.8421782004},
{"learn":[0.05520467727],"iteration":569,"passed_time":1.113413097,"remaining_time":0.8399432136},
{"learn":[0.05515191203],"iteration":570,"passed_time":1.115435515,"remaining_time":0.8380417442},
{"learn":[0.05513267555],"iteration":571,"passed_time":1.117629555,"remaining_time":0.8362682681},
{"learn":[0.05505526188],"iteration":572,"passed_time":1.119372853,"remaining_time":0.8341574315},
{"learn":[0.05499782318],"iteration":573,"passed_time":1.12169464,"remaining_time":0.8324772067},
{"learn":[0.05492561635],"iteration":574,"passed_time":1.123260692,"remaining_time":0.8302361637},
{"learn":[0.05484673122],"iteration":575,"passed_time":1.126686124,"remaining_time":0.8293661744},
{"learn":[0.05481430676],"iteration":576,"passed_time":1.128153761,"remaining_time":0.827052064},
{"learn":[0.05476286046],"iteration":577,"passed_time":1.130207512,"remaining_time":0.8251688061},
{"learn":[0.05467404154],"iteration":578,"passed_time":1.132259346,"remaining_time":0.8232835657},
{"learn":[0.05460482987],"iteration":579,"passed_time":1.133743149,"remaining_time":0.8209864185},
{"learn":[0.05456727829],"iteration":580,"passed_time":1.137862775,"remaining_time":0.8205929482},
{"learn":[0.0544640599],"iteration":581,"passed_time":1.139927901,"remaining_time":0.8187111041},
{"learn":[0.05438261604],"iteration":582,"passed_time":1.142089858,"remaining_time":0.8168978914},
{"learn":[0.0543281894],"iteration":583,"passed_time":1.143586036,"remaining_time":0.8146092312},
{"learn":[0.05424049074],"iteration":584,"passed_time":1.144925468,"remaining_time":0.812212084},
{"learn":[0.05417076989],"iteration":585,"passed_time":1.148408148,"remaining_time":0.811332719},
{"learn":[0.05408667489],"iteration":586,"passed_time":1.15131559,"remaining_time":0.8100397593},
{"learn":[0.05403237203],"iteration":587,"passed_time":1.153495505,"remaining_time":0.8082315443},
{"learn":[0.0539532475],"iteration":588,"passed_time":1.156643317,"remaining_time":0.8070974589},
{"learn":[0.0539006793],"iteration":589,"passed_time":1.160269786,"remaining_time":0.8062891735},
{"learn":[0.05387442814],"iteration":590,"passed_time":1.163376516,"remaining_time":0.8051116667},
{"learn":[0.05383894015],"iteration":591,"passed_time":1.169832929,"remaining_time":0.8062362076},
{"learn":[0.05379355107],"iteration":592,"passed_time":1.174750122,"remaining_time":0.8062787516},
{"learn":[0.05373700741],"iteration":593,"passed_time":1.176840247,"remaining_time":0.8043722901},
{"learn":[0.05369010073],"iteration":594,"passed_time":1.179144618,"remaining_time":0.8026110423},
{"learn":[0.05364843512],"iteration":595,"passed_time":1.180910166,"remaining_time":0.8004827298},
{"learn":[0.05359048857],"iteration":596,"passed_time":1.182583549,"remaining_time":0.7982934175},
{"learn":[0.05353674566],"iteration":597,"passed_time":1.184018104,"remaining_time":0.7959452804},
{"learn":[0.05346736115],"iteration":598,"passed_time":1.185710862,"remaining_time":0.7937730475},
{"learn":[0.05341483068],"iteration":599,"passed_time":1.189999193,"remaining_time":0.793332795},
{"learn":[0.05336436244],"iteration":600,"passed_time":1.191654618,"remaining_time":0.7911317679},
{"learn":[0.05334258625],"iteration":601,"passed_time":1.193522122,"remaining_time":0.7890727652},
{"learn":[0.05327621978],"iteration":602,"passed_time":1.195070716,"remaining_time":0.7868044351},
{"learn":[0.05320024748],"iteration":603,"passed_time":1.196444147,"remaining_time":0.7844236462},
{"learn":[0.05312649198],"iteration":604,"passed_time":1.197999658,"remaining_time":0.7821650658},
{"learn":[0.05307601379],"iteration":605,"passed_time":1.200353486,"remaining_time":0.7804278439},
{"learn":[0.05305504576],"iteration":606,"passed_time":1.201786124,"remaining_time":0.7780921691},
{"learn":[0.05300268126],"iteration":607,"passed_time":1.203779751,"remaining_time":0.7761211551},
{"learn":[0.05294797617],"iteration":608,"passed_time":1.205299845,"remaining_time":0.7738460419},
{"learn":[0.05289762761],"iteration":609,"passed_time":1.206817565,"remaining_time":0.7715718858},
{"learn":[0.05282321685],"iteration":610,"passed_time":1.208185329,"remaining_time":0.7692047351},
{"learn":[0.0527802838],"iteration":611,"passed_time":1.209530511,"remaining_time":0.766826533},
{"learn":[0.05270773933],"iteration":612,"passed_time":1.210901733,"remaining_time":0.7644681417},
{"learn":[0.05269112893],"iteration":613,"passed_time":1.212534993,"remaining_time":0.7622776989},
{"learn":[0.05263398143],"iteration":614,"passed_time":1.214067337,"remaining_time":0.7600258938},
{"learn":[0.0525711621],"iteration":615,"passed_time":1.215514933,"remaining_time":0.7577235946},
{"learn":[0.05251693233],"iteration":616,"passed_time":1.216929321,"remaining_time":0.7554034524},
{"learn":[0.05248484393],"iteration":617,"passed_time":1.218327627,"remaining_time":0.7530763001},
{"learn":[0.05241798],"iteration":618,"passed_time":1.219629892,"remaining_time":0.7506930356},
{"learn":[0.05240314813],"iteration":619,"passed_time":1.220920117,"remaining_time":0.748305878},
{"learn":[0.05232066625],"iteration":620,"passed_time":1.223913349,"remaining_time":0.7469616089},
{"learn":[0.05230369252],"iteration":621,"passed_time":1.225529983,"remaining_time":0.7447754559},
{"learn":[0.05221171509],"iteration":622,"passed_time":1.226962121,"remaining_time":0.7424794858},
{"learn":[0.05215938144],"iteration":623,"passed_time":1.228378509,"remaining_time":0.7401767941},
{"learn":[0.05210187196],"iteration":624,"passed_time":1.230499592,"remaining_time":0.7382997552},
{"learn":[0.05203977765],"iteration":625,"passed_time":1.232518302,"remaining_time":0.7363607745},
{"learn":[0.05202215304],"iteration":626,"passed_time":1.239028547,"remaining_time":0.7370935374},
{"learn":[0.05198059727],"iteration":627,"passed_time":1.2405516,"remaining_time":0.7348490367},
{"learn":[0.05196029195],"iteration":628,"passed_time":1.242421104,"remaining_time":0.7328111758},
{"learn":[0.05192836207],"iteration":629,"passed_time":1.243760619,"remaining_time":0.7304625857},
{"learn":[0.05187775219],"iteration":630,"passed_time":1.250422278,"remaining_time":0.7312295094},
{"learn":[0.05180826584],"iteration":631,"passed_time":1.251764792,"remaining_time":0.7288757019},
{"learn":[0.05178676774],"iteration":632,"passed_time":1.253227596,"remaining_time":0.7265948308},
{"learn":[0.05173002269],"iteration":633,"passed_time":1.254672151,"remaining_time":0.7243060051},
{"learn":[0.05164097503],"iteration":634,"passed_time":1.256516531,"remaining_time":0.7222496594},
{"learn":[0.05155346116],"iteration":635,"passed_time":1.258311995,"remaining_time":0.7201659845},
{"learn":[0.05150351101],"iteration":636,"passed_time":1.260255456,"remaining_time":0.7181675519},
{"learn":[0.05145972517],"iteration":637,"passed_time":1.261993213,"remaining_time":0.7160525755},
{"learn":[0.05144569797],"iteration":638,"passed_time":1.263668638,"remaining_time":0.7139035654},
{"learn":[0.05140127977],"iteration":639,"passed_time":1.265580433,"remaining_time":0.7118889936},
{"learn":[0.05134747805],"iteration":640,"passed_time":1.267128694,"remaining_time":0.7096711406},
{"learn":[0.05128892926],"iteration":641,"passed_time":1.270683623,"remaining_time":0.7085743567},
{"learn":[0.05122073082],"iteration":642,"passed_time":1.271816434,"remaining_time":0.7061251427},
{"learn":[0.05120296404],"iteration":643,"passed_time":1.273008243,"remaining_time":0.7037126313},
{"learn":[0.05115654664],"iteration":644,"passed_time":1.274842581,"remaining_time":0.7016575448},
{"learn":[0.05108763499],"iteration":645,"passed_time":1.276283053,"remaining_time":0.6993873075},
{"learn":[0.05102148045],"iteration":646,"passed_time":1.278052892,"remaining_time":0.6972993369},
{"learn":[0.05092281502],"iteration":647,"passed_time":1.279674485,"remaining_time":0.695131819},
{"learn":[0.05083699854],"iteration":648,"passed_time":1.281680612,"remaining_time":0.6931739517},
{"learn":[0.05078542265],"iteration":649,"passed_time":1.284085564,"remaining_time":0.6914306881},
{"learn":[0.05072720392],"iteration":650,"passed_time":1.28553766,"remaining_time":0.6891745671},
{"learn":[0.05067981252],"iteration":651,"passed_time":1.287712908,"remaining_time":0.6873068894},
{"learn":[0.05061497784],"iteration":652,"passed_time":1.289772658,"remaining_time":0.685376895},
{"learn":[0.05054807155],"iteration":653,"passed_time":1.291555289,"remaining_time":0.6832998932},
{"learn":[0.050501264],"iteration":654,"passed_time":1.293328379,"remaining_time":0.6812187645},
{"learn":[0.05043322964],"iteration":655,"passed_time":1.295715248,"remaining_time":0.6794604349},
{"learn":[0.05037841825],"iteration":656,"passed_time":1.297140886,"remaining_time":0.6771983622},
{"learn":[0.05029725211],"iteration":657,"passed_time":1.299008057,"remaining_time":0.6751683215},
{"learn":[0.05018400297],"iteration":658,"passed_time":1.300258907,"remaining_time":0.6728198594},
{"learn":[0.050146683],"iteration":659,"passed_time":1.30155859,"remaining_time":0.6704998795},
{"learn":[0.05005215935],"iteration":660,"passed_time":1.306482866,"remaining_time":0.6700418936},
{"learn":[0.05002782355],"iteration":661,"passed_time":1.308024877,"remaining_time":0.6678435173},
{"learn":[0.04995523399],"iteration":662,"passed_time":1.309415558,"remaining_time":0.6655702005},
{"learn":[0.04984490636],"iteration":663,"passed_time":1.310757739,"remaining_time":0.6632750006},
{"learn":[0.04979802951],"iteration":664,"passed_time":1.312187586,"remaining_time":0.6610268289},
{"learn":[0.04976125223],"iteration":665,"passed_time":1.315349814,"remaining_time":0.6596499068},
{"learn":[0.04969036726],"iteration":666,"passed_time":1.316847076,"remaining_time":0.6574363962},
{"learn":[0.04965618883],"iteration":667,"passed_time":1.318104634,"remaining_time":0.655105896},
{"learn":[0.04962559319],"iteration":668,"passed_time":1.319405816,"remaining_time":0.6528001872},
{"learn":[0.04957484172],"iteration":669,"passed_time":1.320859204,"remaining_time":0.6505724438},
{"learn":[0.04949566115],"iteration":670,"passed_time":1.322484838,"remaining_time":0.6484314632},
{"learn":[0.04943815624],"iteration":671,"passed_time":1.323980225,"remaining_time":0.6462284432},
{"learn":[0.0493907362],"iteration":672,"passed_time":1.326239722,"remaining_time":0.6443987949},
{"learn":[0.04936585741],"iteration":673,"passed_time":1.327972729,"remaining_time":0.6423132189},
{"learn":[0.04933050118],"iteration":674,"passed_time":1.329407158,"remaining_time":0.6400849281},
{"learn":[0.04928104411],"iteration":675,"passed_time":1.330754132,"remaining_time":0.637817069},
{"learn":[0.04925574982],"iteration":676,"passed_time":1.332099146,"remaining_time":0.635550996},
{"learn":[0.04914900425],"iteration":677,"passed_time":1.33373903,"remaining_time":0.633427681},
{"learn":[0.04911349667],"iteration":678,"passed_time":1.33574999,"remaining_time":0.6314812177},
{"learn":[0.04903012385],"iteration":679,"passed_time":1.337145879,"remaining_time":0.6292451195},
{"learn":[0.04897891599],"iteration":680,"passed_time":1.338759013,"remaining_time":0.6271132529},
{"learn":[0.04891937267],"iteration":681,"passed_time":1.34001928,"remaining_time":0.6248183739},
{"learn":[0.04887667432],"iteration":682,"passed_time":1.341483126,"remaining_time":0.6226210114},
{"learn":[0.04886692663],"iteration":683,"passed_time":1.343435378,"remaining_time":0.6206514321},
{"learn":[0.04884738575],"iteration":684,"passed_time":1.344903432,"remaining_time":0.6184592426},
{"learn":[0.04882908313],"iteration":685,"passed_time":1.346750354,"remaining_time":0.6164425817},
{"learn":[0.04878640204],"iteration":686,"passed_time":1.347937622,"remaining_time":0.6141258742},
{"learn":[0.04872526435],"iteration":687,"passed_time":1.349873333,"remaining_time":0.6121518603},
{"learn":[0.04863610785],"iteration":688,"passed_time":1.352096955,"remaining_time":0.6103079145},
{"learn":[0.04858096051],"iteration":689,"passed_time":1.354038042,"remaining_time":0.6083359317},
{"learn":[0.04855857679],"iteration":690,"passed_time":1.355336266,"remaining_time":0.6060765645},
{"learn":[0.04852284478],"iteration":691,"passed_time":1.357119563,"remaining_time":0.604035875},
{"learn":[0.04845665126],"iteration":692,"passed_time":1.358458703,"remaining_time":0.6017991658},
{"learn":[0.0483978858],"iteration":693,"passed_time":1.361353354,"remaining_time":0.6002509024},
{"learn":[0.0483843397],"iteration":694,"passed_time":1.363091319,"remaining_time":0.5981911544},
{"learn":[0.04830794927],"iteration":695,"passed_time":1.364802285,"remaining_time":0.5961205382},
{"learn":[0.0482456302],"iteration":696,"passed_time":1.366006844,"remaining_time":0.5938308089},
{"learn":[0.04817936142],"iteration":697,"passed_time":1.367230361,"remaining_time":0.5915523913},
{"learn":[0.04809906241],"iteration":698,"passed_time":1.368506128,"remaining_time":0.5892994913},
{"learn":[0.04803371874],"iteration":699,"passed_time":1.370047305,"remaining_time":0.5871631308},
{"learn":[0.0479923096],"iteration":700,"passed_time":1.375467905,"remaining_time":0.5866831721},
{"learn":[0.04790733049],"iteration":701,"passed_time":1.377005541,"remaining_time":0.5845408138},
{"learn":[0.04784061109],"iteration":702,"passed_time":1.378335348,"remaining_time":0.5823123732},
{"learn":[0.04777642542],"iteration":703,"passed_time":1.380412973,"remaining_time":0.5804009091},
{"learn":[0.04773333335],"iteration":704,"passed_time":1.382337643,"remaining_time":0.5784249712},
{"learn":[0.04767030835],"iteration":705,"passed_time":1.387313169,"remaining_time":0.5777196481},
{"learn":[0.04761546071],"iteration":706,"passed_time":1.388803014,"remaining_time":0.5755576847},
{"learn":[0.04758178938],"iteration":707,"passed_time":1.390228402,"remaining_time":0.5733710359},
{"learn":[0.04753483622],"iteration":708,"passed_time":1.391780621,"remaining_time":0.5712385906},
{"learn":[0.04745105996],"iteration":709,"passed_time":1.393128552,"remaining_time":0.5690243383},
{"learn":[0.04741683821],"iteration":710,"passed_time":1.394404569,"remaining_time":0.5667832916},
{"learn":[0.04736440827],"iteration":711,"passed_time":1.396955476,"remaining_time":0.565060642},
{"learn":[0.04732168752],"iteration":712,"passed_time":1.398509445,"remaining_time":0.5629343769},
{"learn":[0.04730170335],"iteration":713,"passed_time":1.400194078,"remaining_time":0.5608620537},
{"learn":[0.04722233543],"iteration":714,"passed_time":1.401558592,"remaining_time":0.5586632152},
{"learn":[0.04717446128],"iteration":715,"passed_time":1.402885191,"remaining_time":0.5564516679},
{"learn":[0.0471220162],"iteration":716,"passed_time":1.404956316,"remaining_time":0.554536454},
{"learn":[0.04708263353],"iteration":717,"passed_time":1.407886716,"remaining_time":0.5529582924},
{"learn":[0.04704774288],"iteration":718,"passed_time":1.409152524,"remaining_time":0.5507258126},
{"learn":[0.04698833046],"iteration":719,"passed_time":1.410790741,"remaining_time":0.5486408439},
{"learn":[0.0469390084],"iteration":720,"passed_time":1.412382668,"remaining_time":0.5465392016},
{"learn":[0.04686589363],"iteration":721,"passed_time":1.414822619,"remaining_time":0.544765496},
{"learn":[0.04680335564],"iteration":722,"passed_time":1.416361922,"remaining_time":0.5426448857},
{"learn":[0.04674044754],"iteration":723,"passed_time":1.417758686,"remaining_time":0.5404715431},
{"learn":[0.04668340572],"iteration":724,"passed_time":1.419678272,"remaining_time":0.538498655},
{"learn":[0.04665742455],"iteration":725,"passed_time":1.421057036,"remaining_time":0.5363218016},
{"learn":[0.04659910297],"iteration":726,"passed_time":1.423680942,"remaining_time":0.5346147142},
{"learn":[0.04655521076],"iteration":727,"passed_time":1.424950667,"remaining_time":0.5323991503},
{"learn":[0.04650854208],"iteration":728,"passed_time":1.426525177,"remaining_time":0.5302994829},
{"learn":[0.04646179249],"iteration":729,"passed_time":1.427860192,"remaining_time":0.5281126738},
{"learn":[0.04640202722],"iteration":730,"passed_time":1.43197936,"remaining_time":0.526952733},
{"learn":[0.046338499],"iteration":731,"passed_time":1.433420998,"remaining_time":0.524804409},
{"learn":[0.04633049032],"iteration":732,"passed_time":1.435006174,"remaining_time":0.5227102982},
{"learn":[0.04627883327],"iteration":733,"passed_time":1.436438188,"remaining_time":0.520562068},
{"learn":[0.04624744501],"iteration":734,"passed_time":1.437759078,"remaining_time":0.5183757219},
{"learn":[0.04616140584],"iteration":735,"passed_time":1.439159258,"remaining_time":0.5162201687},
{"learn":[0.04611424665],"iteration":736,"passed_time":1.440628896,"remaining_time":0.5140914512},
{"learn":[0.04606334765],"iteration":737,"passed_time":1.442725604,"remaining_time":0.5121871384},
{"learn":[0.04601251839],"iteration":738,"passed_time":1.443971662,"remaining_time":0.5099818725},
{"learn":[0.04595615848],"iteration":739,"passed_time":1.445982955,"remaining_time":0.5080480654},
{"learn":[0.04588215075],"iteration":740,"passed_time":1.448247785,"remaining_time":0.5062026671},
{"learn":[0.04584406479],"iteration":741,"passed_time":1.45119106,"remaining_time":0.5045920396},
{"learn":[0.04578827137],"iteration":742,"passed_time":1.453081147,"remaining_time":0.5026135326},
{"learn":[0.04573677172],"iteration":743,"passed_time":1.455222646,"remaining_time":0.5007217706},
{"learn":[0.04573364661],"iteration":744,"passed_time":1.457977091,"remaining_time":0.4990391384},
{"learn":[0.04567796376],"iteration":745,"passed_time":1.459442186,"remaining_time":0.4969146319},
{"learn":[0.04561472209],"iteration":746,"passed_time":1.461134736,"remaining_time":0.4948689266},
{"learn":[0.04555131205],"iteration":747,"passed_time":1.462435002,"remaining_time":0.4926920059},
{"learn":[0.04550177353],"iteration":748,"passed_time":1.469908894,"remaining_time":0.4925862916},
{"learn":[0.04544698218],"iteration":749,"passed_time":1.471352324,"remaining_time":0.4904507745},
{"learn":[0.04536279746],"iteration":750,"passed_time":1.473102164,"remaining_time":0.4884186934},
{"learn":[0.04531159997],"iteration":751,"passed_time":1.474876003,"remaining_time":0.4863952777},
{"learn":[0.04526279295],"iteration":752,"passed_time":1.481018631,"remaining_time":0.48580558},
{"learn":[0.04522306675],"iteration":753,"passed_time":1.482503601,"remaining_time":0.4836815462},
{"learn":[0.04516347119],"iteration":754,"passed_time":1.483932406,"remaining_time":0.4815409793},
{"learn":[0.04510276252],"iteration":755,"passed_time":1.485188089,"remaining_time":0.4793464202},
{"learn":[0.04505531437],"iteration":756,"passed_time":1.486579894,"remaining_time":0.4771980375},
{"learn":[0.04497008312],"iteration":757,"passed_time":1.488708185,"remaining_time":0.4752867821},
{"learn":[0.04494347427],"iteration":758,"passed_time":1.490554815,"remaining_time":0.473285521},
{"learn":[0.04489230197],"iteration":759,"passed_time":1.492119159,"remaining_time":0.4711955239},
{"learn":[0.0448478257],"iteration":760,"passed_time":1.493463382,"remaining_time":0.469037777},
{"learn":[0.0448079832],"iteration":761,"passed_time":1.494738398,"remaining_time":0.4668605496},
{"learn":[0.04475825656],"iteration":762,"passed_time":1.496046955,"remaining_time":0.4646961054},
{"learn":[0.04470909559],"iteration":763,"passed_time":1.49754555,"remaining_time":0.4625926046},
{"learn":[0.04465913062],"iteration":764,"passed_time":1.498907857,"remaining_time":0.4604488187},
{"learn":[0.04460146136],"iteration":765,"passed_time":1.501392849,"remaining_time":0.4586500347},
{"learn":[0.04456081185],"iteration":766,"passed_time":1.502932026,"remaining_time":0.456562141},
{"learn":[0.04449262894],"iteration":767,"passed_time":1.50509215,"remaining_time":0.4546632536},
{"learn":[0.0444543675],"iteration":768,"passed_time":1.506727284,"remaining_time":0.4526059851},
{"learn":[0.04439670342],"iteration":769,"passed_time":1.508049174,"remaining_time":0.4504562468},
{"learn":[0.04434811895],"iteration":770,"passed_time":1.509453604,"remaining_time":0.4483331717},
{"learn":[0.04427656799],"iteration":771,"passed_time":1.511229402,"remaining_time":0.4463216369},
{"learn":[0.04420734881],"iteration":772,"passed_time":1.512895536,"remaining_time":0.4442785079},
{"learn":[0.04412904011],"iteration":773,"passed_time":1.51503391,"remaining_time":0.4423742423},
{"learn":[0.04409213777],"iteration":774,"passed_time":1.516485381,"remaining_time":0.4402699492},
{"learn":[0.04401559551],"iteration":775,"passed_time":1.51853134,"remaining_time":0.4383389434},
{"learn":[0.04393841852],"iteration":776,"passed_time":1.519799856,"remaining_time":0.4361845147},
{"learn":[0.04387481724],"iteration":777,"passed_time":1.522058103,"remaining_time":0.4343147799},
{"learn":[0.04381936204],"iteration":778,"passed_time":1.525285621,"remaining_time":0.4327190274},
{"learn":[0.04379993025],"iteration":779,"passed_time":1.527746489,"remaining_time":0.4309028559},
{"learn":[0.04372031008],"iteration":780,"passed_time":1.531731451,"remaining_time":0.4295124043},
{"learn":[0.04365311545],"iteration":781,"passed_time":1.535841869,"remaining_time":0.4281502908},
{"learn":[0.04360182567],"iteration":782,"passed_time":1.538527649,"remaining_time":0.4263863343},
{"learn":[0.04355770129],"iteration":783,"passed_time":1.540237948,"remaining_time":0.4243512714},
{"learn":[0.0435023221],"iteration":784,"passed_time":1.541934206,"remaining_time":0.4223131901},
{"learn":[0.0434484819],"iteration":785,"passed_time":1.543563798,"remaining_time":0.420257828},
{"learn":[0.04340256696],"iteration":786,"passed_time":1.546994188,"remaining_time":0.4186909302},
{"learn":[0.04337607009],"iteration":787,"passed_time":1.548698696,"remaining_time":0.416654979},
{"learn":[0.04332983511],"iteration":788,"passed_time":1.550228207,"remaining_time":0.4145730692},
{"learn":[0.04326426267],"iteration":789,"passed_time":1.55198488,"remaining_time":0.4125529428},
{"learn":[0.04321779818],"iteration":790,"passed_time":1.553370436,"remaining_time":0.4104354248},
{"learn":[0.04319062317],"iteration":791,"passed_time":1.555479727,"remaining_time":0.4085098272},
{"learn":[0.04312516096],"iteration":792,"passed_time":1.557413022,"remaining_time":0.4065378253},
{"learn":[0.04308139482],"iteration":793,"passed_time":1.558809452,"remaining_time":0.4044266336},
{"learn":[0.04302812639],"iteration":794,"passed_time":1.560109176,"remaining_time":0.4022923032},
{"learn":[0.04297458744],"iteration":795,"passed_time":1.56168552,"remaining_time":0.4002309623},
{"learn":[0.04295752592],"iteration":796,"passed_time":1.563077158,"remaining_time":0.3981237932},
{"learn":[0.04291604457],"iteration":797,"passed_time":1.564584253,"remaining_time":0.3960476431},
{"learn":[0.04287854823],"iteration":798,"passed_time":1.565919268,"remaining_time":0.3939296282},
{"learn":[0.04282922061],"iteration":799,"passed_time":1.567385906,"remaining_time":0.3918464764},
{"learn":[0.04277828931],"iteration":800,"passed_time":1.569637069,"remaining_time":0.3899597712},
{"learn":[0.04274065381],"iteration":801,"passed_time":1.571048458,"remaining_time":0.3878648312},
{"learn":[0.04270525383],"iteration":802,"passed_time":1.572661925,"remaining_time":0.3858211697},
{"learn":[0.04264757093],"iteration":803,"passed_time":1.574079189,"remaining_time":0.3837307475},
{"learn":[0.04258380789],"iteration":804,"passed_time":1.575442245,"remaining_time":0.3816288668},
{"learn":[0.04255303912],"iteration":805,"passed_time":1.57676251,"remaining_time":0.3795185198},
{"learn":[0.04249446205],"iteration":806,"passed_time":1.578262397,"remaining_time":0.3774530887},
{"learn":[0.04244999942],"iteration":807,"passed_time":1.579603662,"remaining_time":0.3753513652},
{"learn":[0.04238293544],"iteration":808,"passed_time":1.581264379,"remaining_time":0.3733269423},
{"learn":[0.04235937834],"iteration":809,"passed_time":1.582541228,"remaining_time":0.3712133745},
{"learn":[0.04231668481],"iteration":810,"passed_time":1.58402174,"remaining_time":0.3691493328},
{"learn":[0.04228082917],"iteration":811,"passed_time":1.585933494,"remaining_time":0.3671865724},
{"learn":[0.04223681175],"iteration":812,"passed_time":1.587915662,"remaining_time":0.3652401339},
{"learn":[0.04217929901],"iteration":813,"passed_time":1.590408446,"remaining_time":0.3634102837},
{"learn":[0.04214373131],"iteration":814,"passed_time":1.592550861,"remaining_time":0.3614992753},
{"learn":[0.04206147245],"iteration":815,"passed_time":1.594069998,"remaining_time":0.3594471564},
{"learn":[0.04205026117],"iteration":816,"passed_time":1.600328539,"remaining_time":0.3584579225},
{"learn":[0.04200131551],"iteration":817,"passed_time":1.601654055,"remaining_time":0.3563582371},
{"learn":[0.04194714248],"iteration":818,"passed_time":1.602937654,"remaining_time":0.3542511787},
{"learn":[0.041882423],"iteration":819,"passed_time":1.604306293,"remaining_time":0.3521647961},
{"learn":[0.04183856094],"iteration":820,"passed_time":1.605592976,"remaining_time":0.3500622932},
{"learn":[0.04179843884],"iteration":821,"passed_time":1.607144445,"remaining_time":0.3480191134},
{"learn":[0.04172366482],"iteration":822,"passed_time":1.609169238,"remaining_time":0.3460789248},
{"learn":[0.04167511287],"iteration":823,"passed_time":1.611258654,"remaining_time":0.344152334},
{"learn":[0.04161454853],"iteration":824,"passed_time":1.612755208,"remaining_time":0.3420995896},
{"learn":[0.04154939751],"iteration":825,"passed_time":1.61425547,"remaining_time":0.340048973},
{"learn":[0.04150602313],"iteration":826,"passed_time":1.61547782,"remaining_time":0.3379415513},
{"learn":[0.04144411665],"iteration":827,"passed_time":1.616777669,"remaining_time":0.3358523661},
{"learn":[0.04139015643],"iteration":828,"passed_time":1.618116809,"remaining_time":0.3337731898},
{"learn":[0.04132642508],"iteration":829,"passed_time":1.619615654,"remaining_time":0.3317285075},
{"learn":[0.04128455892],"iteration":830,"passed_time":1.621072667,"remaining_time":0.3296766314},
{"learn":[0.04124921744],"iteration":831,"passed_time":1.622264476,"remaining_time":0.3275726347},
{"learn":[0.04117977519],"iteration":832,"passed_time":1.623687323,"remaining_time":0.3255171464},
{"learn":[0.04114332361],"iteration":833,"passed_time":1.625064379,"remaining_time":0.323454061},
{"learn":[0.0411208153],"iteration":834,"passed_time":1.626429352,"remaining_time":0.3213902311},
{"learn":[0.04111724384],"iteration":835,"passed_time":1.627875156,"remaining_time":0.3193439301},
{"learn":[0.04108779447],"iteration":836,"passed_time":1.629195463,"remaining_time":0.3172746242},
{"learn":[0.04104368217],"iteration":837,"passed_time":1.630968719,"remaining_time":0.3152946689},
{"learn":[0.04099287401],"iteration":838,"passed_time":1.63309526,"remaining_time":0.3133829998},
{"learn":[0.04094547722],"iteration":839,"passed_time":1.6352888,"remaining_time":0.3114835809},
{"learn":[0.04090398005],"iteration":840,"passed_time":1.636539108,"remaining_time":0.3094051346},
{"learn":[0.04086562862],"iteration":841,"passed_time":1.638083744,"remaining_time":0.3073838854},
{"learn":[0.04085055619],"iteration":842,"passed_time":1.639308428,"remaining_time":0.3053041793},
{"learn":[0.04079456134],"iteration":843,"passed_time":1.640763899,"remaining_time":0.3032691566},
{"learn":[0.0407862542],"iteration":844,"passed_time":1.642063706,"remaining_time":0.301206952},
{"learn":[0.04075492453],"iteration":845,"passed_time":1.643960835,"remaining_time":0.299255282},
{"learn":[0.04068653045],"iteration":846,"passed_time":1.645736549,"remaining_time":0.2972818088},
{"learn":[0.04062610481],"iteration":847,"passed_time":1.64722502,"remaining_time":0.2952573148},
{"learn":[0.04059171102],"iteration":848,"passed_time":1.649563265,"remaining_time":0.2933852214},
{"learn":[0.04056466205],"iteration":849,"passed_time":1.650935904,"remaining_time":0.2913416301},
{"learn":[0.04052214748],"iteration":850,"passed_time":1.652473873,"remaining_time":0.289328563},
{"learn":[0.04050040824],"iteration":851,"passed_time":1.653853304,"remaining_time":0.2872890716},
{"learn":[0.04046207662],"iteration":852,"passed_time":1.655182527,"remaining_time":0.2852424754},
{"learn":[0.04042335243],"iteration":853,"passed_time":1.657000366,"remaining_time":0.283281093},
{"learn":[0.04042044068],"iteration":854,"passed_time":1.658322923,"remaining_time":0.2812360513},
{"learn":[0.04037324119],"iteration":855,"passed_time":1.659799727,"remaining_time":0.2792186456},
{"learn":[0.04032200505],"iteration":856,"passed_time":1.661254239,"remaining_time":0.2771987821},
{"learn":[0.04027536576],"iteration":857,"passed_time":1.662724293,"remaining_time":0.2751828085},
{"learn":[0.04023844406],"iteration":858,"passed_time":1.664102682,"remaining_time":0.2731530596},
{"learn":[0.04021469208],"iteration":859,"passed_time":1.665437614,"remaining_time":0.2711177511},
{"learn":[0.0401661322],"iteration":860,"passed_time":1.666987542,"remaining_time":0.2691187785},
{"learn":[0.04012142743],"iteration":861,"passed_time":1.668297765,"remaining_time":0.2670824729},
{"learn":[0.04010094538],"iteration":862,"passed_time":1.669766861,"remaining_time":0.2650730706},
{"learn":[0.04006750211],"iteration":863,"passed_time":1.671025419,"remaining_time":0.263031779},
{"learn":[0.04003452778],"iteration":864,"passed_time":1.672502265,"remaining_time":0.261026365},
{"learn":[0.03996244199],"iteration":865,"passed_time":1.673935028,"remaining_time":0.2590153507},
{"learn":[0.03991792191],"iteration":866,"passed_time":1.675308417,"remaining_time":0.2569965622},
{"learn":[0.03991530872],"iteration":867,"passed_time":1.67651606,"remaining_time":0.2549540551},
{"learn":[0.03987716046],"iteration":868,"passed_time":1.677884824,"remaining_time":0.2529377583},
{"learn":[0.03981726527],"iteration":869,"passed_time":1.679291546,"remaining_time":0.2509286218},
{"learn":[0.03977283834],"iteration":870,"passed_time":1.681610291,"remaining_time":0.2490559444},
{"learn":[0.03972015578],"iteration":871,"passed_time":1.683355381,"remaining_time":0.2470980376},
{"learn":[0.03967431948],"iteration":872,"passed_time":1.684861268,"remaining_time":0.2451058202},
{"learn":[0.0396290282],"iteration":873,"passed_time":1.686505277,"remaining_time":0.243134628},
{"learn":[0.03958581684],"iteration":874,"passed_time":1.688250742,"remaining_time":0.2411786774},
{"learn":[0.03957694767],"iteration":875,"passed_time":1.689823419,"remaining_time":0.2391987488},
{"learn":[0.03954566807],"iteration":876,"passed_time":1.691135893,"remaining_time":0.2371832552},
{"learn":[0.03952191882],"iteration":877,"passed_time":1.692468366,"remaining_time":0.235172142},
{"learn":[0.03948488916],"iteration":878,"passed_time":1.693893088,"remaining_time":0.2331752714},
{"learn":[0.03947277149],"iteration":879,"passed_time":1.695867173,"remaining_time":0.2312546145},
{"learn":[0.03941416693],"iteration":880,"passed_time":1.697200688,"remaining_time":0.229247312},
{"learn":[0.03934755579],"iteration":881,"passed_time":1.698600077,"remaining_time":0.2272503504},
{"learn":[0.03929124264],"iteration":882,"passed_time":1.699980966,"remaining_time":0.2252522911},
{"learn":[0.03925756107],"iteration":883,"passed_time":1.701703473,"remaining_time":0.2233004558},
{"learn":[0.03918244112],"iteration":884,"passed_time":1.703152944,"remaining_time":0.2213136594},
{"learn":[0.03914163063],"iteration":885,"passed_time":1.704565708,"remaining_time":0.2193233529},
{"learn":[0.03910044344],"iteration":886,"passed_time":1.705922264,"remaining_time":0.2173271881},
{"learn":[0.03905821183],"iteration":887,"passed_time":1.707328861,"remaining_time":0.2153387752},
{"learn":[0.03903571],"iteration":888,"passed_time":1.708569919,"remaining_time":0.2133310023},
{"learn":[0.0390078563],"iteration":889,"passed_time":1.709956808,"remaining_time":0.2113429763},
{"learn":[0.03898955962],"iteration":890,"passed_time":1.711230116,"remaining_time":0.2093424048},
{"learn":[0.03895624966],"iteration":891,"passed_time":1.712605422,"remaining_time":0.2073558134},
{"learn":[0.03891569015],"iteration":892,"passed_time":1.714095017,"remaining_time":0.2053842854},
{"learn":[0.03889330073],"iteration":893,"passed_time":1.71586744,"remaining_time":0.2034473699},
{"learn":[0.0388271671],"iteration":894,"passed_time":1.717268037,"remaining_time":0.2014671999},
{"learn":[0.03881648782],"iteration":895,"passed_time":1.718664218,"remaining_time":0.199487811},
{"learn":[0.03879578694],"iteration":896,"passed_time":1.719970067,"remaining_time":0.1974993499},
{"learn":[0.03875580866],"iteration":897,"passed_time":1.721438787,"remaining_time":0.195530909},
{"learn":[0.03872027306],"iteration":898,"passed_time":1.722914675,"remaining_time":0.193564385},
{"learn":[0.03862540244],"iteration":899,"passed_time":1.725020883,"remaining_time":0.1916689869},
{"learn":[0.03859330405],"iteration":900,"passed_time":1.726236358,"remaining_time":0.1896752491},
{"learn":[0.0385686368],"iteration":901,"passed_time":1.727483542,"remaining_time":0.1876866819},
{"learn":[0.03853531048],"iteration":902,"passed_time":1.728799099,"remaining_time":0.1857071014},
{"learn":[0.03847053792],"iteration":903,"passed_time":1.730238403,"remaining_time":0.1837421313},
{"learn":[0.03846125142],"iteration":904,"passed_time":1.731519669,"remaining_time":0.1817617333},
{"learn":[0.03840621748],"iteration":905,"passed_time":1.733070763,"remaining_time":0.1798108739},
{"learn":[0.03837003707],"iteration":906,"passed_time":1.73440557,"remaining_time":0.1778387189},
{"learn":[0.03836637132],"iteration":907,"passed_time":1.735873332,"remaining_time":0.175881439},
{"learn":[0.03836306536],"iteration":908,"passed_time":1.737173223,"remaining_time":0.1739084305},
{"learn":[0.03832814194],"iteration":909,"passed_time":1.738626569,"remaining_time":0.1719520783},
{"learn":[0.03828370213],"iteration":910,"passed_time":1.740043832,"remaining_time":0.1699933053},
{"learn":[0.03826103862],"iteration":911,"passed_time":1.741398972,"remaining_time":0.1680297254},
{"learn":[0.03820677239],"iteration":912,"passed_time":1.742958858,"remaining_time":0.1660869886},
{"learn":[0.03817997482],"iteration":913,"passed_time":1.744391621,"remaining_time":0.1641331284},
{"learn":[0.03812952695],"iteration":914,"passed_time":1.745736927,"remaining_time":0.1621722828},
{"learn":[0.03809245627],"iteration":915,"passed_time":1.747120774,"remaining_time":0.1602163156},
{"learn":[0.03805687956],"iteration":916,"passed_time":1.748668077,"remaining_time":0.1582763908},
{"learn":[0.03803869648],"iteration":917,"passed_time":1.750097382,"remaining_time":0.1563267814},
{"learn":[0.03799172089],"iteration":918,"passed_time":1.751402064,"remaining_time":0.1543673201},
{"learn":[0.03794350565],"iteration":919,"passed_time":1.752830952,"remaining_time":0.1524200828},
{"learn":[0.03791141892],"iteration":920,"passed_time":1.754425254,"remaining_time":0.1504881596},
{"learn":[0.03788725329],"iteration":921,"passed_time":1.756391756,"remaining_time":0.1485884566},
{"learn":[0.0378296983],"iteration":922,"passed_time":1.758661461,"remaining_time":0.146713903},
{"learn":[0.03780056294],"iteration":923,"passed_time":1.760084724,"remaining_time":0.1447688734},
{"learn":[0.03776962375],"iteration":924,"passed_time":1.76137299,"remaining_time":0.1428140262},
{"learn":[0.03771891679],"iteration":925,"passed_time":1.762683755,"remaining_time":0.1408624167},
{"learn":[0.03770601382],"iteration":926,"passed_time":1.76394523,"remaining_time":0.1389083083},
{"learn":[0.03765781927],"iteration":927,"passed_time":1.765258912,"remaining_time":0.1369597432},
{"learn":[0.03760575794],"iteration":928,"passed_time":1.766628468,"remaining_time":0.1350168151},
{"learn":[0.03756128957],"iteration":929,"passed_time":1.767961942,"remaining_time":0.1330724042},
{"learn":[0.03750205735],"iteration":930,"passed_time":1.769349747,"remaining_time":0.1311333325},
{"learn":[0.03745841545],"iteration":931,"passed_time":1.770909258,"remaining_time":0.1292079716},
{"learn":[0.03741473857],"iteration":932,"passed_time":1.772296063,"remaining_time":0.1272709928},
{"learn":[0.0373748027],"iteration":933,"passed_time":1.773733535,"remaining_time":0.1253387723},
{"learn":[0.03734705994],"iteration":934,"passed_time":1.775765161,"remaining_time":0.1234489149},
{"learn":[0.03729073967],"iteration":935,"passed_time":1.777169966,"remaining_time":0.1215158951},
{"learn":[0.03725533707],"iteration":936,"passed_time":1.778421483,"remaining_time":0.1195736963},
{"learn":[0.03720668393],"iteration":937,"passed_time":1.779665833,"remaining_time":0.1176324964},
{"learn":[0.03717782607],"iteration":938,"passed_time":1.781247676,"remaining_time":0.1157147053},
{"learn":[0.03716390898],"iteration":939,"passed_time":1.782643857,"remaining_time":0.1137857781},
{"learn":[0.03712283626],"iteration":940,"passed_time":1.784647275,"remaining_time":0.1118960566},
{"learn":[0.03709634659],"iteration":941,"passed_time":1.786107829,"remaining_time":0.1099726689},
{"learn":[0.03705283851],"iteration":942,"passed_time":1.788194329,"remaining_time":0.1080880984},
{"learn":[0.03702945756],"iteration":943,"passed_time":1.789654592,"remaining_time":0.1061659504},
{"learn":[0.03699619209],"iteration":944,"passed_time":1.791170978,"remaining_time":0.1042480463},
{"learn":[0.03696004794],"iteration":945,"passed_time":1.792573033,"remaining_time":0.1023244649},
{"learn":[0.03691142542],"iteration":946,"passed_time":1.794028254,"remaining_time":0.1004049604},
{"learn":[0.03685744333],"iteration":947,"passed_time":1.795411977,"remaining_time":0.09848251349},
{"learn":[0.03682061984],"iteration":948,"passed_time":1.79676195,"remaining_time":0.09655938824},
{"learn":[0.03676544522],"iteration":949,"passed_time":1.798064174,"remaining_time":0.09463495651},
{"learn":[0.03672532361],"iteration":950,"passed_time":1.799712183,"remaining_time":0.09272964978},
{"learn":[0.0366784359],"iteration":951,"passed_time":1.801007032,"remaining_time":0.09080707723},
{"learn":[0.03661685149],"iteration":952,"passed_time":1.802642416,"remaining_time":0.08890261651},
{"learn":[0.03659453038],"iteration":953,"passed_time":1.803969722,"remaining_time":0.08698386503},
{"learn":[0.03653912297],"iteration":954,"passed_time":1.806470464,"remaining_time":0.08512164491},
{"learn":[0.03651748256],"iteration":955,"passed_time":1.808077099,"remaining_time":0.0832169376},
{"learn":[0.0364693097],"iteration":956,"passed_time":1.81019889,"remaining_time":0.08133600027},
{"learn":[0.03645445853],"iteration":957,"passed_time":1.811915272,"remaining_time":0.07943678646},
{"learn":[0.03640451839],"iteration":958,"passed_time":1.814005105,"remaining_time":0.07755392004},
{"learn":[0.0363937915],"iteration":959,"passed_time":1.815262122,"remaining_time":0.07563592175},
{"learn":[0.03635727115],"iteration":960,"passed_time":1.816582387,"remaining_time":0.07372186587},
{"learn":[0.03632245608],"iteration":961,"passed_time":1.817828946,"remaining_time":0.07180613299},
{"learn":[0.03629233103],"iteration":962,"passed_time":1.819091504,"remaining_time":0.06989240461},
{"learn":[0.03624863453],"iteration":963,"passed_time":1.820937592,"remaining_time":0.06800181879},
{"learn":[0.03620581204],"iteration":964,"passed_time":1.822471353,"remaining_time":0.06609999726},
{"learn":[0.0361927373],"iteration":965,"passed_time":1.824828264,"remaining_time":0.06422790992},
{"learn":[0.03616087846],"iteration":966,"passed_time":1.826058573,"remaining_time":0.06231637323},
{"learn":[0.03611735158],"iteration":967,"passed_time":1.827566376,"remaining_time":0.0604154174},
{"learn":[0.03609532421],"iteration":968,"passed_time":1.829518504,"remaining_time":0.05852948774},
{"learn":[0.03604490841],"iteration":969,"passed_time":1.830910393,"remaining_time":0.05662609462},
{"learn":[0.03602283237],"iteration":970,"passed_time":1.832713023,"remaining_time":0.05473602233},
{"learn":[0.03598612225],"iteration":971,"passed_time":1.834141203,"remaining_time":0.0528353433},
{"learn":[0.03593871739],"iteration":972,"passed_time":1.835891835,"remaining_time":0.05094458329},
{"learn":[0.03590670726],"iteration":973,"passed_time":1.837448346,"remaining_time":0.04904892914},
{"learn":[0.03586717663],"iteration":974,"passed_time":1.838847068,"remaining_time":0.04714992481},
{"learn":[0.03582672008],"iteration":975,"passed_time":1.840378745,"remaining_time":0.04525521505},
{"learn":[0.03579515789],"iteration":976,"passed_time":1.842434496,"remaining_time":0.04337358588},
{"learn":[0.03574578393],"iteration":977,"passed_time":1.843997798,"remaining_time":0.04148052307},
{"learn":[0.03569365712],"iteration":978,"passed_time":1.845462394,"remaining_time":0.03958601662},
{"learn":[0.03565978579],"iteration":979,"passed_time":1.847874096,"remaining_time":0.03771171624},
{"learn":[0.03560612876],"iteration":980,"passed_time":1.849492522,"remaining_time":0.03582095608},
{"learn":[0.03557376127],"iteration":981,"passed_time":1.850892619,"remaining_time":0.03392674861},
{"learn":[0.03551449881],"iteration":982,"passed_time":1.852422963,"remaining_time":0.03203579896},
{"learn":[0.03549369864],"iteration":983,"passed_time":1.853666355,"remaining_time":0.03014091634},
{"learn":[0.03545877606],"iteration":984,"passed_time":1.855212199,"remaining_time":0.02825196242},
{"learn":[0.0354346887],"iteration":985,"passed_time":1.856529214,"remaining_time":0.02636045538},
{"learn":[0.03540373717],"iteration":986,"passed_time":1.858930125,"remaining_time":0.02448438868},
{"learn":[0.03538275727],"iteration":987,"passed_time":1.860548093,"remaining_time":0.02259775011},
{"learn":[0.03533844813],"iteration":988,"passed_time":1.86190319,"remaining_time":0.02070873114},
{"learn":[0.03533058892],"iteration":989,"passed_time":1.863259788,"remaining_time":0.01882080594},
{"learn":[0.03531269421],"iteration":990,"passed_time":1.864782841,"remaining_time":0.01693546475},
{"learn":[0.03528063759],"iteration":991,"passed_time":1.86660443,"remaining_time":0.01505326153},
{"learn":[0.03524672425],"iteration":992,"passed_time":1.8680964,"remaining_time":0.0131688568},
{"learn":[0.03521018222],"iteration":993,"passed_time":1.869831949,"remaining_time":0.01128671196},
{"learn":[0.03515522566],"iteration":994,"passed_time":1.871459166,"remaining_time":0.009404317419},
{"learn":[0.03513467569],"iteration":995,"passed_time":1.872983719,"remaining_time":0.007522022969},
{"learn":[0.03510964437],"iteration":996,"passed_time":1.874432065,"remaining_time":0.005640216846},
{"learn":[0.03510677819],"iteration":997,"passed_time":1.875692998,"remaining_time":0.003758903804},
{"learn":[0.03506804029],"iteration":998,"passed_time":1.877370423,"remaining_time":0.001879249673},
{"learn":[0.03502226761],"iteration":999,"passed_time":1.879094222,"remaining_time":0}
]}